{
    "accessors": {
        "attrbute_1": {
            "bufferView": "bufferView_25",
            "byteOffset": 0,
            "byteStride": 12,
            "count": 2523,
            "max": [
                49.55694580078125,
                19.973312377929688,
                170.1590118408203,
                0
            ],
            "min": [
                -49.557010650634766,
                -11.921015739440918,
                -0.3329100012779236,
                0
            ],
            "type": 35665
        },
        "attrbute_10": {
            "bufferView": "bufferView_25",
            "byteOffset": 162964,
            "byteStride": 16,
            "count": 362,
            "max": [
                1,
                -1,
                -1,
                -1
            ],
            "min": [
                0,
                -1,
                -1,
                -1
            ],
            "type": 35666
        },
        "attrbute_11": {
            "bufferView": "bufferView_25",
            "byteOffset": 168756,
            "byteStride": 12,
            "count": 362,
            "max": [
                1,
                0,
                0
            ],
            "min": [
                1,
                0,
                0
            ],
            "type": 35665
        },
        "attrbute_13": {
            "bufferView": "bufferView_25",
            "byteOffset": 173100,
            "byteStride": 12,
            "count": 964,
            "max": [
                100.89999389648438,
                56.37446212768555,
                153.33802795410156,
                0
            ],
            "min": [
                -100.89996337890625,
                -11.696418762207031,
                56.29308319091797,
                0
            ],
            "type": 35665
        },
        "attrbute_14": {
            "bufferView": "bufferView_25",
            "byteOffset": 184668,
            "byteStride": 12,
            "count": 964,
            "max": [
                0.9959197044372559,
                0.9807376265525818,
                0.9657325744628906,
                0
            ],
            "min": [
                -0.9959197044372559,
                -0.9939667582511902,
                -0.9769660234451294,
                0
            ],
            "type": 35665
        },
        "attrbute_15": {
            "bufferView": "bufferView_25",
            "byteOffset": 196236,
            "byteStride": 8,
            "count": 964,
            "max": [
                1.9899015426635742,
                1.9835002422332764
            ],
            "min": [
                1.01910400390625,
                0.014246523380279541
            ],
            "type": 35664
        },
        "attrbute_16": {
            "bufferView": "bufferView_25",
            "byteOffset": 203948,
            "byteStride": 16,
            "count": 964,
            "max": [
                20,
                21,
                22,
                -1
            ],
            "min": [
                0,
                -1,
                -1,
                -1
            ],
            "type": 35666
        },
        "attrbute_17": {
            "bufferView": "bufferView_25",
            "byteOffset": 219372,
            "byteStride": 12,
            "count": 964,
            "max": [
                1,
                0.9998787045478821,
                0.965481162071228
            ],
            "min": [
                0.00012127949594287202,
                0,
                0
            ],
            "type": 35665
        },
        "attrbute_19": {
            "bufferView": "bufferView_25",
            "byteOffset": 230940,
            "byteStride": 12,
            "count": 514,
            "max": [
                10.612699508666992,
                26.551496505737305,
                175.73500061035156,
                0
            ],
            "min": [
                -11.172699928283691,
                -7.457482814788818,
                138.2259979248047,
                0
            ],
            "type": 35665
        },
        "attrbute_2": {
            "bufferView": "bufferView_25",
            "byteOffset": 30276,
            "byteStride": 12,
            "count": 2523,
            "max": [
                0.9994056224822998,
                0.9999592304229736,
                0.9999791979789734,
                0
            ],
            "min": [
                -0.9994056224822998,
                -0.9997408390045166,
                -0.9994143843650818,
                0
            ],
            "type": 35665
        },
        "attrbute_20": {
            "bufferView": "bufferView_25",
            "byteOffset": 237108,
            "byteStride": 12,
            "count": 514,
            "max": [
                0.9987985491752625,
                0.9975900650024414,
                0.993798017501831,
                0
            ],
            "min": [
                -0.9965807199478149,
                -0.9989432692527771,
                -0.9799984097480774,
                0
            ],
            "type": 35665
        },
        "attrbute_21": {
            "bufferView": "bufferView_25",
            "byteOffset": 243276,
            "byteStride": 8,
            "count": 514,
            "max": [
                0.9933350086212158,
                0.9873600006103516
            ],
            "min": [
                0.007619000039994717,
                0.007773995399475098
            ],
            "type": 35664
        },
        "attrbute_22": {
            "bufferView": "bufferView_25",
            "byteOffset": 247388,
            "byteStride": 16,
            "count": 514,
            "max": [
                2,
                2,
                3,
                -1
            ],
            "min": [
                0,
                -1,
                -1,
                -1
            ],
            "type": 35666
        },
        "attrbute_23": {
            "bufferView": "bufferView_25",
            "byteOffset": 255612,
            "byteStride": 12,
            "count": 514,
            "max": [
                1,
                0.9997740387916565,
                0.7662582397460938
            ],
            "min": [
                0.0002259688772028312,
                0,
                0
            ],
            "type": 35665
        },
        "attrbute_3": {
            "bufferView": "bufferView_25",
            "byteOffset": 60552,
            "byteStride": 8,
            "count": 2523,
            "max": [
                0.9875274896621704,
                1.988150954246521
            ],
            "min": [
                0.009398000314831734,
                0.004364132881164551
            ],
            "type": 35664
        },
        "attrbute_4": {
            "bufferView": "bufferView_25",
            "byteOffset": 80736,
            "byteStride": 16,
            "count": 2523,
            "max": [
                57,
                57,
                58,
                -1
            ],
            "min": [
                0,
                -1,
                -1,
                -1
            ],
            "type": 35666
        },
        "attrbute_5": {
            "bufferView": "bufferView_25",
            "byteOffset": 121104,
            "byteStride": 12,
            "count": 2523,
            "max": [
                1,
                0.9998993873596191,
                0.9991639256477356
            ],
            "min": [
                0.00010063916124636307,
                0,
                0
            ],
            "type": 35665
        },
        "attrbute_7": {
            "bufferView": "bufferView_25",
            "byteOffset": 151380,
            "byteStride": 12,
            "count": 362,
            "max": [
                30.64790916442871,
                20.241106033325195,
                155.71499633789062,
                0
            ],
            "min": [
                -30.647903442382812,
                -1.7014228105545044,
                122.73200225830078,
                0
            ],
            "type": 35665
        },
        "attrbute_8": {
            "bufferView": "bufferView_25",
            "byteOffset": 155724,
            "byteStride": 12,
            "count": 362,
            "max": [
                0.9949731230735779,
                0.9933704137802124,
                0.8972244262695312,
                0
            ],
            "min": [
                -0.9949731230735779,
                -0.9978908896446228,
                -0.9997121691703796,
                0
            ],
            "type": 35665
        },
        "attrbute_9": {
            "bufferView": "bufferView_25",
            "byteOffset": 160068,
            "byteStride": 8,
            "count": 362,
            "max": [
                3.978621482849121,
                1.957690715789795
            ],
            "min": [
                3.0265417098999023,
                0.028478622436523438
            ],
            "type": 35664
        },
        "indices_12": {
            "bufferView": "bufferView_27",
            "byteOffset": 23190,
            "count": 1668,
            "type": 5123
        },
        "indices_18": {
            "bufferView": "bufferView_27",
            "byteOffset": 26526,
            "count": 4248,
            "type": 5123
        },
        "indices_24": {
            "bufferView": "bufferView_27",
            "byteOffset": 35022,
            "count": 2508,
            "type": 5123
        },
        "indices_6": {
            "bufferView": "bufferView_27",
            "byteOffset": 0,
            "count": 11595,
            "type": 5123
        }
    },
    "animations": {},
    "asset": {},
    "bufferViews": {
        "bufferView_25": {
            "buffer": "queenofpain.bin",
            "byteLength": 261780,
            "byteOffset": 0,
            "target": 34962
        },
        "bufferView_26": {
            "buffer": "queenofpain.bin",
            "byteLength": 6656,
            "byteOffset": 261780
        },
        "bufferView_27": {
            "buffer": "queenofpain.bin",
            "byteLength": 40038,
            "byteOffset": 268436,
            "target": 34963
        }
    },
    "buffers": {
        "queenofpain.bin": {
            "byteLength": 308474,
            "path": "queenofpain.bin"
        }
    },
    "cameras": {},
    "images": {
        "image_0": {
            "path": "textures/queenofpain_color.png"
        },
        "image_1": {
            "path": "textures/queenofpain_armour_color.png"
        },
        "image_2": {
            "path": "textures/queenofpain_wing_color.png"
        },
        "image_3": {
            "path": "textures/queenofpain_hair_color.png"
        }
    },
    "lights": {},
    "materials": {
        "Material #35": {
            "instanceTechnique": {
                "technique": "technique_0",
                "values": {
                    "ambient": [
                        0.5879999995231628,
                        0.5879999995231628,
                        0.5879999995231628
                    ],
                    "diffuse": "Map #7",
                    "emission": [
                        0,
                        0,
                        0
                    ],
                    "shininess": 2,
                    "specular": [
                        0.8999999761581421,
                        0.8999999761581421,
                        0.8999999761581421
                    ],
                    "transparency": 1
                }
            },
            "name": "Material #35"
        },
        "Material #46": {
            "instanceTechnique": {
                "technique": "technique_0",
                "values": {
                    "ambient": [
                        0.5879999995231628,
                        0.5879999995231628,
                        0.5879999995231628
                    ],
                    "diffuse": "Map #8",
                    "emission": [
                        0,
                        0,
                        0
                    ],
                    "shininess": 2,
                    "specular": [
                        0.8999999761581421,
                        0.8999999761581421,
                        0.8999999761581421
                    ],
                    "transparency": 1
                }
            },
            "name": "Material #46"
        },
        "Material #57": {
            "instanceTechnique": {
                "technique": "technique_0",
                "values": {
                    "ambient": [
                        0.5879999995231628,
                        0.5879999995231628,
                        0.5879999995231628
                    ],
                    "diffuse": "Map #9",
                    "emission": [
                        0,
                        0,
                        0
                    ],
                    "shininess": 2,
                    "specular": [
                        0.8999999761581421,
                        0.8999999761581421,
                        0.8999999761581421
                    ],
                    "transparency": 1
                }
            },
            "name": "Material #57"
        },
        "Material #68": {
            "instanceTechnique": {
                "technique": "technique_0",
                "values": {
                    "ambient": [
                        0.5879999995231628,
                        0.5879999995231628,
                        0.5879999995231628
                    ],
                    "diffuse": "Map #6",
                    "emission": [
                        0,
                        0,
                        0
                    ],
                    "shininess": 2,
                    "specular": [
                        0.8999999761581421,
                        0.8999999761581421,
                        0.8999999761581421
                    ],
                    "transparency": 1
                }
            },
            "name": "Material #68"
        }
    },
    "meshes": {
        "QueenOfPain_model_LOD0-mesh": {
            "name": "QueenOfPain_model_LOD0-mesh",
            "primitives": [
                {
                    "attributes": {
                        "JOINT": "attrbute_4",
                        "NORMAL": "attrbute_2",
                        "POSITION": "attrbute_1",
                        "TEXCOORD_0": "attrbute_3",
                        "WEIGHT": "attrbute_5"
                    },
                    "indices": "indices_6",
                    "material": "Material #35"
                }
            ]
        },
        "hair_model_LOD0-mesh": {
            "name": "hair_model_LOD0-mesh",
            "primitives": [
                {
                    "attributes": {
                        "JOINT": "attrbute_22",
                        "NORMAL": "attrbute_20",
                        "POSITION": "attrbute_19",
                        "TEXCOORD_0": "attrbute_21",
                        "WEIGHT": "attrbute_23"
                    },
                    "indices": "indices_24",
                    "material": "Material #68"
                }
            ]
        },
        "shoulders_model_LOD0-mesh": {
            "name": "shoulders_model_LOD0-mesh",
            "primitives": [
                {
                    "attributes": {
                        "JOINT": "attrbute_10",
                        "NORMAL": "attrbute_8",
                        "POSITION": "attrbute_7",
                        "TEXCOORD_0": "attrbute_9",
                        "WEIGHT": "attrbute_11"
                    },
                    "indices": "indices_12",
                    "material": "Material #46"
                }
            ]
        },
        "wings_model_LOD0-mesh": {
            "name": "wings_model_LOD0-mesh",
            "primitives": [
                {
                    "attributes": {
                        "JOINT": "attrbute_16",
                        "NORMAL": "attrbute_14",
                        "POSITION": "attrbute_13",
                        "TEXCOORD_0": "attrbute_15",
                        "WEIGHT": "attrbute_17"
                    },
                    "indices": "indices_18",
                    "material": "Material #57"
                }
            ]
        }
    },
    "nodes": {
        "Hair_R0C0": {
            "children": [
                "Hair_R1C0"
            ],
            "jointId": "Hair_R0C0",
            "matrix": [
                -0.6454894542694093,
                9.746619853653146e-8,
                -0.7637691497802733,
                0,
                -2.293439871088616e-7,
                -0.9999999999999998,
                6.621493753300623e-8,
                0,
                -0.7637691497802596,
                2.1790690593401436e-7,
                0.6454894542694254,
                0,
                -2.6315279006958,
                -4.330890988057949e-7,
                14.161911010742188,
                1
            ],
            "name": "Hair_R0C0"
        },
        "Hair_R1C0": {
            "children": [
                "Hair_R2C0"
            ],
            "jointId": "Hair_R1C0",
            "matrix": [
                0.8147488236427308,
                2.3781687730206613e-8,
                -0.5798140764236452,
                0,
                -6.6638312223892365e-9,
                0.9999999999999999,
                3.165211026612271e-8,
                0,
                0.5798140764236456,
                -2.1924736459480792e-8,
                0.8147488236427305,
                0,
                12.097953796386719,
                -0.0000017432421373086965,
                0.000007629394517039145,
                1
            ],
            "name": "Hair_R1C0"
        },
        "Hair_R2C0": {
            "children": [],
            "jointId": "Hair_R2C0",
            "matrix": [
                0.9999999999999999,
                -7.105427357601002e-15,
                0,
                0,
                7.105427370835892e-15,
                1.0000000000000002,
                3.554636052172097e-8,
                0,
                2.7755575615628914e-17,
                -3.5546360521721e-8,
                1,
                0,
                12.371353149414034,
                -0.0000019073495423072,
                0.0000152587890625,
                1
            ],
            "name": "Hair_R2C0"
        },
        "Head_0": {
            "children": [
                "Head_1"
            ],
            "jointId": "Head_0",
            "matrix": [
                0.9913986325263977,
                6.438282795784286e-9,
                -0.13087455928325656,
                0,
                -6.494141525954524e-9,
                0.9999999999999999,
                -1.7763568220294576e-15,
                0,
                0.1308745592832566,
                8.499196712101229e-10,
                0.9913986325263976,
                0,
                6.294189453124972,
                -0.0000011966781130468007,
                -0.000032424926761365214,
                1
            ],
            "name": "Head_0"
        },
        "Head_1": {
            "children": [
                "Hair_R0C0"
            ],
            "jointId": "Head_1",
            "matrix": [
                0.19193992018699615,
                9.152408608770187e-8,
                -0.9814067482948308,
                0,
                -8.865953304850526e-9,
                1,
                9.152408608770151e-8,
                0,
                0.9814067482948305,
                -8.866019375413973e-9,
                0.19193992018699543,
                0,
                9.053878784179688,
                9.829705049924002e-8,
                -0.000011444091796875,
                1
            ],
            "name": "Head_1"
        },
        "Hip_Lo0_0": {
            "children": [
                "thigh_R",
                "thigh_L"
            ],
            "jointId": "Hip_Lo0_0",
            "matrix": [
                1.0000000000000002,
                -2.6469779601696886e-23,
                0,
                0,
                2.6469779601696886e-23,
                1.0000000000000002,
                0,
                0,
                0,
                0,
                1,
                0,
                -0.7488315105438241,
                -4.768372150465439e-7,
                -2.9407196044921875,
                1
            ],
            "name": "Hip_Lo0_0"
        },
        "QueenOfPain_model_LOD0": {
            "children": [],
            "instanceSkin": {
                "skeletons": [
                    "Root_0"
                ],
                "skin": "skin_0",
                "sources": [
                    "QueenOfPain_model_LOD0-mesh"
                ]
            },
            "matrix": [
                1,
                0,
                0,
                0,
                0,
                1,
                0,
                0,
                0,
                0,
                1,
                0,
                0,
                0,
                0,
                1
            ],
            "name": "QueenOfPain_model_LOD0"
        },
        "Root_0": {
            "children": [
                "Spine_0",
                "Hip_Lo0_0"
            ],
            "jointId": "Root_0",
            "matrix": [
                -1.629206851037603e-7,
                -1.0000000000000002,
                0,
                0,
                1.0000000000000002,
                -1.629206851037603e-7,
                0,
                0,
                0,
                0,
                1,
                0,
                0,
                3.630470037460327,
                106.82960510253906,
                1
            ],
            "name": "Root_0"
        },
        "Spine_0": {
            "children": [
                "Spine_1"
            ],
            "jointId": "Spine_0",
            "matrix": [
                0.08658694475889295,
                0,
                0.9962443113327027,
                0,
                -8.709497507920408e-8,
                1.0000000000000002,
                7.569717297428795e-9,
                0,
                -0.9962443113327027,
                -8.742331216179348e-8,
                0.0865869447588929,
                0,
                0.7411127090454097,
                2.9739973683717825e-7,
                4.04144287109375,
                1
            ],
            "name": "Spine_0"
        },
        "Spine_1": {
            "children": [
                "wingL_0",
                "Spine_2",
                "wingR_0"
            ],
            "jointId": "Spine_1",
            "matrix": [
                0.9709458351135256,
                -6.617444900424222e-24,
                0.2392995655536652,
                0,
                -3.937660152111542e-8,
                0.9999999999999998,
                1.5976856104771284e-7,
                0,
                -0.23929956555366533,
                -1.6454942256834047e-7,
                0.9709458351135255,
                0,
                6.709083557128906,
                3.8680525449308345e-7,
                -9.536743146298932e-7,
                1
            ],
            "name": "Spine_1"
        },
        "Spine_2": {
            "children": [
                "Spine_3",
                "chest2_0"
            ],
            "jointId": "Spine_2",
            "matrix": [
                0.9907582998275757,
                7.815094349439281e-9,
                0.13564084470272064,
                0,
                -7.8879931787795e-9,
                0.9999999999999999,
                2.6645352533101114e-15,
                0,
                -0.13564084470272064,
                -1.0699366976893672e-9,
                0.9907582998275756,
                0,
                6.39569091796875,
                2.492049588909142e-7,
                0.000005722045900213857,
                1
            ],
            "name": "Spine_2"
        },
        "Spine_3": {
            "children": [
                "clavicle_R",
                "Head_0",
                "clavicle_L"
            ],
            "jointId": "Spine_3",
            "matrix": [
                0.9383755326271057,
                1.7763568261653607e-15,
                -0.34561744332313543,
                0,
                -3.20152918996616e-15,
                1,
                -3.55271369120821e-15,
                0,
                0.3456174433231353,
                4.440283935668738e-15,
                0.9383755326271057,
                0,
                15.052566528320312,
                0.0000019073488601861754,
                0.000034332275390625,
                1
            ],
            "name": "Spine_3"
        },
        "ankle_L": {
            "children": [
                "toeBase_L"
            ],
            "jointId": "ankle_L",
            "matrix": [
                0.6218683123588562,
                0.093236044049263,
                0.7775518894195558,
                0,
                0.17238237294129313,
                0.952237088615043,
                -0.25205000096800245,
                0,
                -0.7639138435959751,
                0.2907781299303138,
                0.5760937839251368,
                0,
                40.38151550292968,
                -0.0000057220458984375,
                -0.000003814697265625,
                1
            ],
            "name": "ankle_L"
        },
        "ankle_R": {
            "children": [
                "toeBase_R"
            ],
            "jointId": "ankle_R",
            "matrix": [
                0.6218681335449219,
                0.09323512017726894,
                0.7775517702102661,
                0,
                0.17238183613014652,
                0.9522371783524222,
                -0.252048449969132,
                0,
                -0.7639136766502364,
                0.29077677917873707,
                0.5760940705148152,
                0,
                -40.38151550292969,
                -0.0000152587890625,
                0.00001049041748046875,
                1
            ],
            "name": "ankle_R"
        },
        "bicep_L": {
            "children": [
                "sh_pad_L4_0",
                "elbow_L"
            ],
            "jointId": "bicep_L",
            "matrix": [
                0.40972855687141396,
                -0.23441304266452778,
                -0.8815744519233701,
                0,
                -0.8973247574231483,
                0.07028873142108227,
                -0.43573877675712674,
                0,
                0.1641075420792215,
                0.9695928453263956,
                -0.18154525948625683,
                0,
                9.99715805053711,
                1.7763568394002505e-15,
                -0.00003051757815342171,
                1
            ],
            "name": "bicep_L"
        },
        "bicep_R": {
            "children": [
                "sh_pad_R3_0",
                "elbow_R"
            ],
            "jointId": "bicep_R",
            "matrix": [
                0.4097281396389006,
                -0.23441416025161732,
                -0.8815740942955016,
                0,
                -0.8973245723981464,
                0.07028923483275706,
                -0.43573866580776865,
                0,
                0.16410848747686455,
                0.9695925226417148,
                -0.18154611477819588,
                0,
                -9.997156143188473,
                9.536743146298932e-7,
                -0.0000457763671875,
                1
            ],
            "name": "bicep_R"
        },
        "chest2_0": {
            "children": [],
            "jointId": "chest2_0",
            "matrix": [
                -0.28691911697387734,
                -2.736273926517501e-7,
                -0.957955002784729,
                0,
                -4.968859172916637e-7,
                1,
                -1.3681365371513479e-7,
                0,
                0.9579550027846945,
                4.3673989756887937e-7,
                -0.28691911697399164,
                0,
                3.9054183959960938,
                4.235164736271502e-22,
                -7.0713653564453125,
                1
            ],
            "name": "chest2_0"
        },
        "clavicle_L": {
            "children": [
                "bicep_L"
            ],
            "jointId": "clavicle_L",
            "matrix": [
                -0.031493734568357336,
                0.8838265538215639,
                0.46675321459770197,
                0,
                0.016619994703097378,
                -0.46645715630700557,
                0.8843873673622606,
                0,
                0.9993654506848392,
                0.03561009818218386,
                0.0000012852253166162342,
                0,
                1.52520751953125,
                4.640922546386719,
                -2.7108898162841797,
                1
            ],
            "name": "clavicle_L"
        },
        "clavicle_R": {
            "children": [
                "bicep_R"
            ],
            "jointId": "clavicle_R",
            "matrix": [
                0.031493458896875236,
                0.8838263750076292,
                -0.46675336360931374,
                0,
                -0.01662208190539355,
                -0.4664572638890201,
                -0.8843872410479198,
                0,
                -0.9993655092726652,
                0.035610834523824235,
                6.817282519264167e-7,
                0,
                1.52520751953125,
                -4.640924453735352,
                -2.7108898162841797,
                1
            ],
            "name": "clavicle_R"
        },
        "elbow_L": {
            "children": [
                "wrist_L"
            ],
            "jointId": "elbow_L",
            "matrix": [
                0.9587579369544983,
                -8.940696705206364e-8,
                -0.2842240333557129,
                0,
                1.1865325211246613e-7,
                0.9999998807907037,
                8.568167289557671e-8,
                0,
                0.28422400266814046,
                -1.1587209114427566e-7,
                0.9587578334377654,
                0,
                26.016563415527344,
                -0.00002288818359375,
                -9.536743199589637e-7,
                1
            ],
            "name": "elbow_L"
        },
        "elbow_R": {
            "children": [
                "wrist_R"
            ],
            "jointId": "elbow_R",
            "matrix": [
                0.9587579965591432,
                -5.960464477539063e-8,
                -0.28422424197196966,
                0,
                -2.1060927485327952e-7,
                1.0000003576278826,
                -9.201466788441581e-7,
                0,
                0.2842242696417617,
                9.420580026620051e-7,
                0.9587580898959324,
                0,
                -26.016601562500014,
                0,
                -0.000005722045900213857,
                1
            ],
            "name": "elbow_R"
        },
        "hair_model_LOD0": {
            "children": [],
            "instanceSkin": {
                "skeletons": [
                    "Root_0"
                ],
                "skin": "skin_3",
                "sources": [
                    "hair_model_LOD0-mesh"
                ]
            },
            "matrix": [
                1,
                0,
                0,
                0,
                0,
                1,
                0,
                0,
                0,
                0,
                1,
                0,
                0,
                0,
                0,
                1
            ],
            "name": "hair_model_LOD0"
        },
        "index_0_L": {
            "children": [
                "index_1_L"
            ],
            "jointId": "index_0_L",
            "matrix": [
                0.9680213928222661,
                0.25086379051208507,
                0.0013137161731720526,
                0,
                0.0713138164168648,
                -0.28019551009830856,
                0.9572903783071254,
                0,
                0.24051758461498368,
                -0.9265838573438065,
                -0.2891252954208314,
                0,
                11.735214233398438,
                -0.02494049072265625,
                -3.1347579956054616,
                1
            ],
            "name": "index_0_L"
        },
        "index_0_R": {
            "children": [
                "index_1_R"
            ],
            "jointId": "index_0_R",
            "matrix": [
                0.9680215120315552,
                0.2508641183376312,
                0.0013135969638824463,
                0,
                0.07131399719804404,
                -0.28019541999093067,
                0.9572902771378238,
                0,
                0.24051778724688597,
                -0.9265836803377239,
                -0.2891252474665286,
                0,
                -11.735206604003913,
                0.0249176025390625,
                3.134773254394524,
                1
            ],
            "name": "index_0_R"
        },
        "index_1_L": {
            "children": [
                "index_2_L"
            ],
            "jointId": "index_1_L",
            "matrix": [
                0.6095837950706486,
                -7.450580596923828e-8,
                -0.7927218675613406,
                0,
                2.5786962160045945e-7,
                1.0000004768371409,
                1.0430808643213663e-7,
                0,
                0.7927219366631382,
                -2.680033028557016e-7,
                0.6095838482082716,
                0,
                5.565456390380852,
                -0.000003814697269177714,
                0,
                1
            ],
            "name": "index_1_L"
        },
        "index_1_R": {
            "children": [
                "index_2_R"
            ],
            "jointId": "index_1_R",
            "matrix": [
                0.6095840334892272,
                2.384185791015625e-7,
                -0.7927219271659848,
                0,
                -3.8142805947050107e-7,
                1.0000004768371604,
                7.450579514456379e-9,
                0,
                0.7927218147979107,
                2.978244478535341e-7,
                0.6095839470809792,
                0,
                -5.565456390380859,
                -0.0000057220458984375,
                -0.000022888183579539145,
                1
            ],
            "name": "index_1_R"
        },
        "index_2_L": {
            "children": [],
            "jointId": "index_2_L",
            "matrix": [
                0.9542064666748049,
                -0.04246409237384782,
                -0.29611885547637923,
                0,
                0.04055613111824863,
                0.999097589373752,
                -0.012585654984097971,
                0,
                0.2963862102892499,
                -1.2175617775112002e-7,
                0.9550680020241591,
                0,
                2.7200698852539062,
                0.0000019073486328125,
                -0.0000038146972585195726,
                1
            ],
            "name": "index_2_L"
        },
        "index_2_R": {
            "children": [],
            "jointId": "index_2_R",
            "matrix": [
                0.9776110649108882,
                -0.06550897657871246,
                -0.19996166229248047,
                0,
                0.06418012068441187,
                0.997851260234109,
                -0.013127609948941688,
                0,
                0.20039211794928574,
                1.331238288215797e-7,
                0.9797155157711992,
                0,
                -2.7201080322265625,
                -0.000005722045891332073,
                0.000011444091803980427,
                1
            ],
            "name": "index_2_R"
        },
        "knee_L": {
            "children": [
                "ankle_L"
            ],
            "jointId": "knee_L",
            "matrix": [
                0.9968859553337097,
                1.192092894952701e-7,
                -0.07885572314262392,
                0,
                -1.5877385248219689e-7,
                0.9999999403953521,
                -4.954636090050146e-7,
                0,
                0.07885574188468827,
                5.064410906578665e-7,
                0.9968861922697287,
                0,
                44.61017227172853,
                0.000003814697265625,
                0,
                1
            ],
            "name": "knee_L"
        },
        "knee_R": {
            "children": [
                "ankle_R"
            ],
            "jointId": "knee_R",
            "matrix": [
                0.9968861937522889,
                -4.4703483575991854e-7,
                -0.07885557413101202,
                0,
                4.1111762841272714e-7,
                1.0000000000000295,
                -4.7171488536503284e-7,
                0,
                0.07885556021362965,
                4.3782706275752314e-7,
                0.9968860178073139,
                0,
                -44.61017227172851,
                0.000011444091793322286,
                -0.000003814697266513178,
                1
            ],
            "name": "knee_R"
        },
        "knife_L_1": {
            "children": [],
            "jointId": "knife_L_1",
            "matrix": [
                -0.8281497955322268,
                -0.4273158609867096,
                -0.36272454261779796,
                0,
                -0.5110892896240622,
                0.8413829847071483,
                0.17567654978979316,
                0,
                0.23012093397891129,
                0.3308712021017537,
                -0.9151879126467755,
                0,
                56.980716705322266,
                74.14236450195312,
                36.9314079284668,
                1
            ],
            "name": "knife_L_1"
        },
        "mid_0_L": {
            "children": [
                "mid_1_L"
            ],
            "jointId": "mid_0_L",
            "matrix": [
                0.8797568678855896,
                0.4481362998485565,
                0.15874922275543205,
                0,
                -0.06115823116709518,
                -0.22446095288819184,
                0.9725620831708851,
                0,
                0.4714734244145347,
                -0.8653270842233676,
                -0.1700638592304552,
                0,
                11.768619537353501,
                -1.0003509521484375,
                -1.0802001953125,
                1
            ],
            "name": "mid_0_L"
        },
        "mid_0_R": {
            "children": [
                "mid_1_R"
            ],
            "jointId": "mid_0_R",
            "matrix": [
                0.8797569870948794,
                0.44813638925552357,
                0.15874929726123801,
                0,
                -0.061158027589296504,
                -0.22446138961433743,
                0.9725619037141395,
                0,
                0.47147344911431616,
                -0.8653268899254999,
                -0.17006433147662256,
                0,
                -11.768592834472663,
                1.0003585815429688,
                1.080219268798821,
                1
            ],
            "name": "mid_0_R"
        },
        "mid_1_L": {
            "children": [
                "mid_2_L"
            ],
            "jointId": "mid_1_L",
            "matrix": [
                0.7515394687652591,
                1.49011611910721e-7,
                -0.6596886515617372,
                0,
                5.5967037310145074e-8,
                1.0000003576278687,
                2.8964133652782664e-7,
                0,
                0.6596884259894632,
                -2.545975374690368e-7,
                0.7515392117856905,
                0,
                5.608825683593764,
                0,
                0.00000762939453125,
                1
            ],
            "name": "mid_1_L"
        },
        "mid_1_R": {
            "children": [
                "mid_2_R"
            ],
            "jointId": "mid_1_R",
            "matrix": [
                0.7515389919281004,
                1.9371509552001953e-7,
                -0.6596891880035402,
                0,
                -8.199538020781105e-8,
                1.000000119209305,
                2.0023428556718847e-7,
                0,
                0.6596891210203942,
                -9.639238604530753e-8,
                0.7515389156187331,
                0,
                -5.608802795410156,
                0,
                0.0000038146972585195726,
                1
            ],
            "name": "mid_1_R"
        },
        "mid_2_L": {
            "children": [],
            "jointId": "mid_2_L",
            "matrix": [
                0.8574533462524419,
                -0.030191652476787567,
                -0.5136744379997253,
                0,
                0.0258997406065134,
                0.9995439644000889,
                -0.015515790097223314,
                0,
                0.5139089169709141,
                3.14382425925519e-8,
                0.857844749472898,
                0,
                2.6441802978515625,
                -0.000005722045894884786,
                -0.000015258789055394573,
                1
            ],
            "name": "mid_2_L"
        },
        "mid_2_R": {
            "children": [],
            "jointId": "mid_2_R",
            "matrix": [
                0.8829410076141355,
                -0.08702652156352995,
                -0.4613466560840607,
                0,
                0.07713192610308786,
                0.9962058685694765,
                -0.040302429214333246,
                0,
                0.46310385847464597,
                1.1127487400952596e-7,
                0.8863039806518711,
                0,
                -2.6442031860351562,
                0.0000019073486292597863,
                -0.000011444091782664145,
                1
            ],
            "name": "mid_2_R"
        },
        "pinky_0_L": {
            "children": [
                "pinky_1_L"
            ],
            "jointId": "pinky_0_L",
            "matrix": [
                0.9212816357612612,
                0.36351677775382996,
                0.1381880939006806,
                0,
                -0.0932499949508796,
                -0.13847842460871218,
                0.9859658291776355,
                0,
                0.3775510514243238,
                -0.9212379110301704,
                -0.09367965728315382,
                0,
                11.217876434326179,
                -0.33841705322265625,
                3.151000976562507,
                1
            ],
            "name": "pinky_0_L"
        },
        "pinky_0_R": {
            "children": [
                "pinky_1_R"
            ],
            "jointId": "pinky_0_R",
            "matrix": [
                0.9212809801101685,
                0.36351698637008667,
                0.13818851113319391,
                0,
                -0.093250094499501,
                -0.13847924943222972,
                0.9859654523156204,
                0,
                0.3775515674584292,
                -0.9212376424787194,
                -0.0936803391217295,
                0,
                -11.217864990234375,
                0.3384094238281392,
                -3.150981903076179,
                1
            ],
            "name": "pinky_0_R"
        },
        "pinky_1_L": {
            "children": [
                "pinky_2_L"
            ],
            "jointId": "pinky_1_L",
            "matrix": [
                0.8182583451271057,
                4.1723251345548995e-7,
                -0.5748502016067506,
                0,
                -2.416480359701545e-7,
                1.0000001192092738,
                3.8184215730985294e-7,
                0,
                0.5748502630037673,
                -1.7353410733389474e-7,
                0.8182584325212628,
                0,
                3.8947601318359375,
                0.000003814697265625,
                -0.00003814697265625,
                1
            ],
            "name": "pinky_1_L"
        },
        "pinky_1_R": {
            "children": [
                "pinky_2_R"
            ],
            "jointId": "pinky_1_R",
            "matrix": [
                0.8182587623596191,
                -2.980232233218416e-8,
                -0.5748502612113953,
                0,
                3.118739311247509e-8,
                1.000000119209289,
                -7.450580683660002e-9,
                0,
                0.5748503089445174,
                -1.1831577717558162e-8,
                0.8182588303043492,
                0,
                -3.894752502441392,
                -0.000005722045894884786,
                0.0000152587890625,
                1
            ],
            "name": "pinky_1_R"
        },
        "pinky_2_L": {
            "children": [],
            "jointId": "pinky_2_L",
            "matrix": [
                0.9781124591827393,
                -0.08755062520504,
                -0.18876197934150685,
                0,
                0.08596428226368122,
                0.9961601722822879,
                -0.016590790008619433,
                0,
                0.18948972864067948,
                8.70342482695019e-7,
                0.981883051439381,
                0,
                1.7020339965820312,
                0.000005722045901990214,
                0.000015258789055394573,
                1
            ],
            "name": "pinky_2_L"
        },
        "pinky_2_R": {
            "children": [],
            "jointId": "pinky_2_R",
            "matrix": [
                0.9589054584503174,
                -0.08797334134578699,
                -0.2697418034076692,
                0,
                0.08468645786371551,
                0.9961227178204239,
                -0.02382254842812756,
                0,
                0.2707917488097143,
                9.38535835992571e-8,
                0.9626378800022013,
                0,
                -1.702056884765625,
                -3.552713678800501e-15,
                0,
                1
            ],
            "name": "pinky_2_R"
        },
        "ring_0_L": {
            "children": [
                "ring_1_L"
            ],
            "jointId": "ring_0_L",
            "matrix": [
                0.8689889907836914,
                0.4843640923500062,
                0.10123993456363675,
                0,
                -0.04174111056092747,
                -0.1321133250253257,
                0.990355404079613,
                0,
                0.4930678563205265,
                -0.8648340130639414,
                -0.09458715201661924,
                0,
                11.3853530883789,
                -0.9535598754882812,
                1.42022705078125,
                1
            ],
            "name": "ring_0_L"
        },
        "ring_0_R": {
            "children": [
                "ring_1_R"
            ],
            "jointId": "ring_0_R",
            "matrix": [
                0.8689886927604681,
                0.4843641221523288,
                0.10123983025550845,
                0,
                -0.04174040959330577,
                -0.1321143200339698,
                0.9903550841771931,
                0,
                0.4930677911758636,
                -0.864833317834736,
                -0.09458831045971677,
                0,
                -11.3853530883789,
                0.9535369873046875,
                -1.4202308654785227,
                1
            ],
            "name": "ring_0_R"
        },
        "ring_1_L": {
            "children": [
                "ring_2_L"
            ],
            "jointId": "ring_1_L",
            "matrix": [
                0.7056015729904176,
                4.0233135231715345e-7,
                -0.7086083292961118,
                0,
                -9.530200673069089e-8,
                0.9999997615814179,
                4.7287901738953496e-7,
                0,
                0.7086082396360683,
                -2.6613241246864483e-7,
                0.7056014837106667,
                0,
                5.589195251464844,
                0.00000762939453125,
                0.000007629394524144573,
                1
            ],
            "name": "ring_1_L"
        },
        "ring_1_R": {
            "children": [
                "ring_2_R"
            ],
            "jointId": "ring_1_R",
            "matrix": [
                0.7056021094322206,
                -4.470348355378739e-8,
                -0.7086085677146912,
                0,
                -2.608401989956377e-7,
                1.0000001192093302,
                -3.2281981043815085e-7,
                0,
                0.7086085384206351,
                4.1261587274687983e-7,
                0.7056020802624262,
                0,
                -5.589179992675767,
                0.0000019073486328125,
                0.0000038146972585195726,
                1
            ],
            "name": "ring_1_R"
        },
        "ring_2_L": {
            "children": [],
            "jointId": "ring_2_L",
            "matrix": [
                0.9818929433822631,
                0.02226155996322636,
                -0.18812605738639832,
                0,
                -0.02186386278130939,
                0.9997524622376659,
                0.0041890890469390984,
                0,
                0.1881726573280229,
                -7.467006982175839e-8,
                0.9821361552594832,
                0,
                2.6143112182617045,
                -0.0000019073486363652137,
                -0.000013351440433240214,
                1
            ],
            "name": "ring_2_L"
        },
        "ring_2_R": {
            "children": [],
            "jointId": "ring_2_R",
            "matrix": [
                0.9636794328689577,
                -0.0858378261327744,
                -0.25289112329483027,
                0,
                0.0830265707376151,
                0.9963089888132981,
                -0.021788029105209605,
                0,
                0.25382801821108947,
                -7.205714636082661e-9,
                0.9672496134601865,
                0,
                -2.61431884765625,
                0.0000019073486328125,
                -0.0000019073486257070726,
                1
            ],
            "name": "ring_2_R"
        },
        "sh_pad_L4_0": {
            "children": [],
            "jointId": "sh_pad_L4_0",
            "matrix": [
                0.9999998807907102,
                -5.066394806463315e-7,
                -1.5646219254927818e-7,
                0,
                5.066397139041889e-7,
                1.0000001192092483,
                7.189810276586606e-7,
                0,
                1.5646186556084185e-7,
                -7.189811068800123e-7,
                1.000000119209249,
                0,
                8.980941772460952,
                0.01071166992188921,
                -0.13156414031982422,
                1
            ],
            "name": "sh_pad_L4_0"
        },
        "sh_pad_R3_0": {
            "children": [],
            "jointId": "sh_pad_R3_0",
            "matrix": [
                -0.9600032567977907,
                -0.24805277585983276,
                -0.12985897064208982,
                0,
                0.2775143606862681,
                -0.9045114359857755,
                -0.32379832803102754,
                0,
                -0.03713984445599478,
                -0.34688512759930024,
                0.9371719938828136,
                0,
                -9.03460693359375,
                0.00074005126953125,
                -0.0984039306640625,
                1
            ],
            "name": "sh_pad_R3_0"
        },
        "shoulders_model_LOD0": {
            "children": [],
            "instanceSkin": {
                "skeletons": [
                    "Root_0"
                ],
                "skin": "skin_1",
                "sources": [
                    "shoulders_model_LOD0-mesh"
                ]
            },
            "matrix": [
                1,
                0,
                0,
                0,
                0,
                1,
                0,
                0,
                0,
                0,
                1,
                0,
                0,
                0,
                0,
                1
            ],
            "name": "shoulders_model_LOD0"
        },
        "thigh_L": {
            "children": [
                "knee_L"
            ],
            "jointId": "thigh_L",
            "matrix": [
                -0.02561390958726407,
                0.1521178185939789,
                -0.9880305528640748,
                0,
                -0.06804199094340808,
                0.9857974021323601,
                0.15353793600046453,
                0,
                0.9973534956566973,
                0.07116025044556533,
                -0.014899721626257283,
                0,
                -0.2640352249145508,
                9.654452323913572,
                -3.4978485107421875,
                1
            ],
            "name": "thigh_L"
        },
        "thigh_R": {
            "children": [
                "knee_R"
            ],
            "jointId": "thigh_R",
            "matrix": [
                0.02561378292739396,
                0.15211816132068656,
                0.9880302548408509,
                0,
                0.06804281735132726,
                0.9857970513637113,
                -0.153538282961429,
                0,
                -0.9973535541848803,
                0.0711610784684481,
                0.014899447615508666,
                0,
                -0.26403236389160156,
                -9.654449462890623,
                -3.4978485107421875,
                1
            ],
            "name": "thigh_R"
        },
        "thumb_0_L": {
            "children": [
                "thumb_1_L"
            ],
            "jointId": "thumb_0_L",
            "matrix": [
                0.9123589992523197,
                0.33056771755218506,
                -0.24150827527046204,
                0,
                0.2914113562272056,
                -0.9387310531758315,
                -0.1840202297652475,
                0,
                -0.2875424744245653,
                0.09751426185327428,
                -0.9527909425928177,
                0,
                1.7927780151367188,
                2.399932861328125,
                -2.2389068603515625,
                1
            ],
            "name": "thumb_0_L"
        },
        "thumb_0_R": {
            "children": [
                "thumb_1_R"
            ],
            "jointId": "thumb_0_R",
            "matrix": [
                0.9123587608337405,
                0.3305681943893433,
                -0.24150821566581737,
                0,
                0.29141182691546125,
                -0.9387306285883823,
                -0.18402005700313132,
                0,
                -0.287542402914191,
                0.09751398316124432,
                -0.9527908126613307,
                0,
                -1.7927703857421875,
                -2.399963378906236,
                2.2389183044433523,
                1
            ],
            "name": "thumb_0_R"
        },
        "thumb_1_L": {
            "children": [
                "thumb_2_L"
            ],
            "jointId": "thumb_1_L",
            "matrix": [
                0.9979805946350102,
                -5.215406418956903e-7,
                -0.06352141499519354,
                0,
                5.244928912295777e-7,
                0.9999999999999691,
                2.980232241545089e-8,
                0,
                0.06352143778655978,
                -6.305869264255914e-8,
                0.9979809527091239,
                0,
                5.965007781982422,
                -0.000007629394524144573,
                0.000015258789069605427,
                1
            ],
            "name": "thumb_1_L"
        },
        "thumb_1_R": {
            "children": [
                "thumb_2_R"
            ],
            "jointId": "thumb_1_R",
            "matrix": [
                0.9979804754257202,
                7.450580599699386e-8,
                -0.06352129578590382,
                0,
                -4.525442454106354e-8,
                0.9999999999999991,
                4.6193600859723016e-7,
                0,
                0.06352128979216909,
                -4.581284545751574e-7,
                0.9979803812578597,
                0,
                -5.9649925231933665,
                -0.0000152587890625,
                0.000003814697272730427,
                1
            ],
            "name": "thumb_1_R"
        },
        "thumb_2_L": {
            "children": [],
            "jointId": "thumb_2_L",
            "matrix": [
                0.9767575860023499,
                0.009043335914611816,
                -0.21415551006793979,
                0,
                -0.008833530325086436,
                0.9999590513213168,
                0.0019366667036194857,
                0,
                0.21416420367303146,
                9.529812830533224e-8,
                0.9767972413282077,
                0,
                4.8562774658203125,
                0.000007629394524144573,
                -0.000011444091803980427,
                1
            ],
            "name": "thumb_2_L"
        },
        "thumb_2_R": {
            "children": [],
            "jointId": "thumb_2_R",
            "matrix": [
                0.9862140417099,
                -0.017183750867843656,
                -0.16458001732826233,
                0,
                0.01694927506525959,
                0.999852420264851,
                -0.002829030132804458,
                0,
                0.16460432516357476,
                5.172573974282502e-7,
                0.9863596477225585,
                0,
                -4.856269836425781,
                0,
                -0.00000762939453125,
                1
            ],
            "name": "thumb_2_R"
        },
        "toeBase_L": {
            "children": [],
            "jointId": "toeBase_L",
            "matrix": [
                0.7496991157531738,
                -0.10761512815952305,
                0.6529709100723268,
                0,
                0.08062336986391562,
                0.9941926613815941,
                0.0712848012917805,
                0,
                -0.6568497045614492,
                -0.0007974366884325339,
                0.754021073291751,
                0,
                17.774396896362305,
                0.000003814697269177714,
                -9.5367431640625e-7,
                1
            ],
            "name": "toeBase_L"
        },
        "toeBase_R": {
            "children": [],
            "jointId": "toeBase_R",
            "matrix": [
                0.7496990561485288,
                -0.10761471092700961,
                0.6529706716537473,
                0,
                0.08062331895492485,
                0.9941923642738222,
                0.07128420889901918,
                0,
                -0.6568495101646115,
                -0.0007970411883172029,
                0.7540211311451319,
                0,
                -17.774391174316406,
                0,
                0.00000476837158203125,
                1
            ],
            "name": "toeBase_R"
        },
        "wingL_0": {
            "children": [
                "wingL_1"
            ],
            "jointId": "wingL_0",
            "matrix": [
                -0.06516672670841214,
                0.9161019921302794,
                0.3956140577793122,
                0,
                0.1481233329815202,
                -0.3831841903407195,
                0.9117181399168388,
                0,
                0.9868195639165491,
                0.11801332466300979,
                -0.11072518816778801,
                0,
                10.471939086914077,
                8.648473739624022,
                9.10775089263916,
                1
            ],
            "name": "wingL_0"
        },
        "wingL_1": {
            "children": [
                "wingL_f1_0",
                "wingL_f0_0",
                "wingL_f2_0"
            ],
            "jointId": "wingL_1",
            "matrix": [
                0.16270318627357477,
                -0.6306627988815302,
                0.758809685707092,
                0,
                0.6014164196851307,
                0.6730649965459541,
                0.43044348661216647,
                0,
                -0.7821931260640477,
                0.3863261732111645,
                0.48880090298903484,
                0,
                29.43317031860352,
                -0.000004768371583807607,
                0.000022888183607960855,
                1
            ],
            "name": "wingL_1"
        },
        "wingL_f0_0": {
            "children": [
                "wingL_f0_1"
            ],
            "jointId": "wingL_f0_0",
            "matrix": [
                -0.038684219121933316,
                -0.02194350957870503,
                -0.9990100860595705,
                0,
                -0.49340165768906746,
                0.86980146797024,
                3.613549026254548e-7,
                0,
                0.8689408876738784,
                0.4929135052895509,
                -0.044474577932267834,
                0,
                26.41643524169922,
                0.00000762939453125,
                0.00000762939453125,
                1
            ],
            "name": "wingL_f0_0"
        },
        "wingL_f0_1": {
            "children": [],
            "jointId": "wingL_f0_1",
            "matrix": [
                1.0000002384185787,
                -4.619359970370329e-7,
                4.17232513649779e-7,
                0,
                4.619358577664934e-7,
                0.9999999403953712,
                3.725290305400808e-9,
                0,
                -4.172324157281082e-7,
                -3.725097792728338e-9,
                0.9999999999999878,
                0,
                19.81456756591797,
                0.00000762939453125,
                -0.00003051757815342171,
                1
            ],
            "name": "wingL_f0_1"
        },
        "wingL_f1_0": {
            "children": [
                "wingL_f1_1"
            ],
            "jointId": "wingL_f1_0",
            "matrix": [
                -0.37817806005477933,
                0.20655253529548656,
                -0.9023951292037966,
                0,
                -0.8990390980165767,
                0.15045095683788173,
                0.411208877979217,
                0,
                0.22070253601300774,
                0.9667990690543993,
                0.1288016060309252,
                0,
                24.622581481933594,
                0.9234161376953125,
                -0.8342056274414134,
                1
            ],
            "name": "wingL_f1_0"
        },
        "wingL_f1_1": {
            "children": [],
            "jointId": "wingL_f1_1",
            "matrix": [
                -0.9957702159881595,
                0.09145322442054749,
                -0.00882843136787409,
                0,
                0.09133004810814416,
                0.9957295645576262,
                0.013472110033006551,
                0,
                0.010022798318029214,
                0.012608825225820658,
                -0.9998703002908356,
                0,
                39.89475250244142,
                0.0000152587890625,
                0.000030517578125,
                1
            ],
            "name": "wingL_f1_1"
        },
        "wingL_f2_0": {
            "children": [
                "wingL_f2_1"
            ],
            "jointId": "wingL_f2_0",
            "matrix": [
                0.964115679264069,
                -0.053046345710754284,
                0.26012909412384044,
                0,
                0.015688173084397294,
                -0.9667385700308726,
                -0.2552854084666112,
                0,
                0.2650186698633734,
                0.25020550511702044,
                -0.9312152029964509,
                0,
                20.453384399414062,
                1.6791229248046733,
                -1.921855926513686,
                1
            ],
            "name": "wingL_f2_0"
        },
        "wingL_f2_1": {
            "children": [],
            "jointId": "wingL_f2_1",
            "matrix": [
                0.984597325325012,
                -0.1548524796962737,
                0.08116790652275069,
                0,
                0.15591930558728773,
                0.9877454431167235,
                -0.006935007893785761,
                0,
                -0.07909934702925808,
                0.019483838870057724,
                0.9966762695834496,
                0,
                -45.70353698730467,
                -0.0000457763671875,
                1.0658141036401503e-14,
                1
            ],
            "name": "wingL_f2_1"
        },
        "wingR_0": {
            "children": [
                "wingR_1"
            ],
            "jointId": "wingR_0",
            "matrix": [
                0.06516687572002418,
                0.9161019921302797,
                -0.3956141769886017,
                0,
                -0.14812364129153086,
                -0.38318410319970736,
                -0.9117177699815879,
                0,
                -0.986819554419574,
                0.11801361409455866,
                0.11072545489397684,
                0,
                10.471939086914062,
                -8.64847755432129,
                9.107754707336428,
                1
            ],
            "name": "wingR_0"
        },
        "wingR_1": {
            "children": [
                "wingR_f2_0",
                "wingR_f0_0",
                "wingR_f1_0"
            ],
            "jointId": "wingR_1",
            "matrix": [
                0.16270342469215404,
                -0.6306634545326231,
                0.7588090896606446,
                0,
                0.6014166623382156,
                0.6730645460722667,
                0.43044379089619084,
                0,
                -0.7821925402336561,
                0.3863256901904509,
                0.488801339452534,
                0,
                -29.433162689208984,
                9.5367431640625e-7,
                -0.0000152587890625,
                1
            ],
            "name": "wingR_1"
        },
        "wingR_f0_0": {
            "children": [
                "wingR_f0_1"
            ],
            "jointId": "wingR_f0_0",
            "matrix": [
                -0.03868308663368114,
                -0.021943390369414673,
                -0.999010801315308,
                0,
                -0.4934016251018523,
                0.8698015324497482,
                -9.68572569544357e-8,
                0,
                0.868941168166637,
                0.49291357187682083,
                -0.04447351455594012,
                0,
                -26.4164276123047,
                1.4210854715202004e-14,
                0.000011444091796875,
                1
            ],
            "name": "wingR_f0_0"
        },
        "wingR_f0_1": {
            "children": [],
            "jointId": "wingR_f0_1",
            "matrix": [
                0.9999999999999998,
                1.341104507446289e-7,
                5.960464477539063e-8,
                0,
                -1.3411046583672315e-7,
                1.0000001192092833,
                -1.4901161207725444e-8,
                0,
                -5.9604639834898165e-8,
                1.4901149633650412e-8,
                0.9999998807907082,
                0,
                -19.81452178955079,
                -0.000007629394530361822,
                -0.00003051757809657829,
                1
            ],
            "name": "wingR_f0_1"
        },
        "wingR_f1_0": {
            "children": [
                "wingr_f1_1"
            ],
            "jointId": "wingR_f1_0",
            "matrix": [
                -0.37817743420600897,
                0.20655268430709844,
                -0.9023957252502444,
                0,
                -0.8990394764526138,
                0.15045156724502634,
                0.4112083060062486,
                0,
                0.2207030857469962,
                0.9667993242466479,
                0.12880166169676202,
                0,
                -24.622573852539077,
                -0.923431396484375,
                0.8342094421386577,
                1
            ],
            "name": "wingR_f1_0"
        },
        "wingR_f2_0": {
            "children": [
                "wingR_f2_1"
            ],
            "jointId": "wingR_f2_0",
            "matrix": [
                0.9641153812408448,
                -0.053045898675918635,
                0.2601300477981568,
                0,
                0.015689037384260307,
                -0.966738756172981,
                -0.25528603453220117,
                0,
                0.2650196723650987,
                0.2502063791471212,
                -0.9312154527040787,
                0,
                -20.453392028808608,
                -1.6791229248046875,
                1.9218788146972656,
                1
            ],
            "name": "wingR_f2_0"
        },
        "wingR_f2_1": {
            "children": [],
            "jointId": "wingR_f2_1",
            "matrix": [
                0.9845976233482364,
                -0.15485206246376065,
                0.08116795122623438,
                0,
                0.15591880627318533,
                0.9877452082460898,
                -0.00693504514731115,
                0,
                -0.07909935662116971,
                0.019483840948734288,
                0.9966760312542962,
                0,
                45.703514099121065,
                0.000022888183579539145,
                0.000019073486328125,
                1
            ],
            "name": "wingR_f2_1"
        },
        "wingr_f1_1": {
            "children": [],
            "jointId": "wingr_f1_1",
            "matrix": [
                -0.9957700967788699,
                0.09145307540893549,
                -0.008828192949295155,
                0,
                0.09132989156719035,
                0.9957293254627901,
                0.013472080238309897,
                0,
                0.010022555546569889,
                0.012608818959833179,
                -0.9998700624382129,
                0,
                -39.89468002319337,
                0.000007629394545460855,
                -1.4210854715202004e-14,
                1
            ],
            "name": "wingr_f1_1"
        },
        "wings_model_LOD0": {
            "children": [],
            "instanceSkin": {
                "skeletons": [
                    "Root_0"
                ],
                "skin": "skin_2",
                "sources": [
                    "wings_model_LOD0-mesh"
                ]
            },
            "matrix": [
                1,
                0,
                0,
                0,
                0,
                1,
                0,
                0,
                0,
                0,
                1,
                0,
                0,
                0,
                0,
                1
            ],
            "name": "wings_model_LOD0"
        },
        "wrist_L": {
            "children": [
                "thumb_0_L",
                "index_0_L",
                "mid_0_L",
                "ring_0_L",
                "pinky_0_L",
                "knife_L_1"
            ],
            "jointId": "wrist_L",
            "matrix": [
                0.9999995231628418,
                8.940696705206364e-8,
                2.9802322387695312e-8,
                0,
                -8.940703383197857e-8,
                1.0000000000000029,
                8.046627044400179e-7,
                0,
                -2.9802261103384353e-8,
                -8.046626111812838e-7,
                0.9999998807910013,
                0,
                29.0004234313965,
                0.000015258789048289145,
                7.105427357601002e-15,
                1
            ],
            "name": "wrist_L"
        },
        "wrist_R": {
            "children": [
                "thumb_0_R",
                "index_0_R",
                "mid_0_R",
                "ring_0_R",
                "pinky_0_R"
            ],
            "jointId": "wrist_R",
            "matrix": [
                0.9999998807907103,
                -4.172325135387567e-7,
                -5.960464477539063e-8,
                0,
                4.172325792084486e-7,
                1.0000000000000415,
                2.6822090143374666e-7,
                0,
                5.960453991482595e-8,
                -2.6822092627498684e-7,
                0.9999999999999823,
                0,
                -29.000442504882805,
                0.000007629394545460855,
                0.00000762939453125,
                1
            ],
            "name": "wrist_R"
        }
    },
    "samplers": {
        "sampler_0": {
            "magFilter": 9729,
            "minFilter": 9987,
            "wrapS": 10497,
            "wrapT": 10497
        }
    },
    "scene": "scene_0",
    "scenes": {
        "scene_0": {
            "nodes": [
                "Root_0",
                "QueenOfPain_model_LOD0",
                "shoulders_model_LOD0",
                "wings_model_LOD0",
                "hair_model_LOD0"
            ]
        }
    },
    "shaders": {},
    "skins": {
        "skin_0": {
            "bindShapeMatrix": [
                1,
                0,
                0,
                0,
                0,
                1,
                0,
                0,
                0,
                0,
                1,
                0,
                0,
                0,
                0,
                1
            ],
            "inverseBindMatrices": {
                "bufferView": "bufferView_26",
                "byteOffset": 0,
                "count": 59,
                "type": 5126
            },
            "joints": [
                "Head_1",
                "Spine_3",
                "clavicle_R",
                "Head_0",
                "Spine_2",
                "chest2_0",
                "clavicle_L",
                "ring_1_L",
                "ring_0_L",
                "wrist_L",
                "pinky_0_L",
                "mid_0_L",
                "mid_1_L",
                "thumb_0_L",
                "index_0_L",
                "elbow_L",
                "mid_2_L",
                "thumb_1_L",
                "thumb_2_L",
                "knee_R",
                "bicep_L",
                "sh_pad_L4_0",
                "knee_L",
                "ankle_L",
                "toeBase_L",
                "thigh_L",
                "Hip_Lo0_0",
                "thigh_R",
                "Spine_0",
                "Spine_1",
                "Root_0",
                "bicep_R",
                "sh_pad_R3_0",
                "wingL_0",
                "pinky_2_R",
                "pinky_1_R",
                "pinky_0_R",
                "thumb_0_R",
                "wrist_R",
                "elbow_R",
                "index_0_R",
                "thumb_1_R",
                "ring_0_R",
                "ring_1_R",
                "ring_2_R",
                "mid_0_R",
                "mid_1_R",
                "mid_2_R",
                "thumb_2_R",
                "index_1_R",
                "index_2_R",
                "ankle_R",
                "toeBase_R",
                "index_1_L",
                "index_2_L",
                "pinky_1_L",
                "ring_2_L",
                "pinky_2_L",
                "wingR_0"
            ]
        },
        "skin_1": {
            "bindShapeMatrix": [
                1,
                0,
                0,
                0,
                0,
                1,
                0,
                0,
                0,
                0,
                1,
                0,
                0,
                0,
                0,
                1
            ],
            "inverseBindMatrices": {
                "bufferView": "bufferView_26",
                "byteOffset": 3776,
                "count": 2,
                "type": 5126
            },
            "joints": [
                "sh_pad_L4_0",
                "sh_pad_R3_0",
                "bicep_L",
                "clavicle_L",
                "Spine_3",
                "Spine_2",
                "Spine_1",
                "Spine_0",
                "Root_0",
                "bicep_R",
                "clavicle_R"
            ]
        },
        "skin_2": {
            "bindShapeMatrix": [
                1,
                0,
                0,
                0,
                0,
                1,
                0,
                0,
                0,
                0,
                1,
                0,
                0,
                0,
                0,
                1
            ],
            "inverseBindMatrices": {
                "bufferView": "bufferView_26",
                "byteOffset": 4480,
                "count": 23,
                "type": 5126
            },
            "joints": [
                "wingR_0",
                "wingR_1",
                "Spine_2",
                "wingR_f2_1",
                "clavicle_R",
                "bicep_R",
                "clavicle_L",
                "bicep_L",
                "wingL_0",
                "wingL_1",
                "wingL_f2_1",
                "wingL_f0_1",
                "wingL_f0_0",
                "wingL_f1_0",
                "wingL_f2_0",
                "wingL_f1_1",
                "wingR_f0_1",
                "wingr_f1_1",
                "wingR_f1_0",
                "wingR_f0_0",
                "wingR_f2_0",
                "Spine_0",
                "Spine_1",
                "Root_0",
                "Spine_3"
            ]
        },
        "skin_3": {
            "bindShapeMatrix": [
                1,
                0,
                0,
                0,
                0,
                1,
                0,
                0,
                0,
                0,
                1,
                0,
                0,
                0,
                0,
                1
            ],
            "inverseBindMatrices": {
                "bufferView": "bufferView_26",
                "byteOffset": 6080,
                "count": 4,
                "type": 5126
            },
            "joints": [
                "Hair_R1C0",
                "Hair_R0C0",
                "Head_1",
                "Head_0",
                "Spine_3",
                "Spine_2",
                "Spine_1",
                "Spine_0",
                "Root_0"
            ]
        }
    },
    "techniques": {
        "technique_0": {
            "parameters": {},
            "pass": "defaultPass",
            "passes": {
                "defaultPass": {
                    "instanceProgram": {
                        "attributes": {},
                        "program": "",
                        "uniforms": {}
                    },
                    "states": {
                        "blendEnable": false,
                        "cullFaceEnable": false,
                        "depthMask": true,
                        "depthTestEnable": true
                    }
                }
            }
        }
    },
    "textures": {
        "Map #6": {
            "format": 6408,
            "internalFormat": 6408,
            "sampler": "sampler_0",
            "source": "image_3",
            "target": 3553
        },
        "Map #7": {
            "format": 6408,
            "internalFormat": 6408,
            "sampler": "sampler_0",
            "source": "image_0",
            "target": 3553
        },
        "Map #8": {
            "format": 6408,
            "internalFormat": 6408,
            "sampler": "sampler_0",
            "source": "image_1",
            "target": 3553
        },
        "Map #9": {
            "format": 6408,
            "internalFormat": 6408,
            "sampler": "sampler_0",
            "source": "image_2",
            "target": 3553
        }
    }
}