{
    "idle": [
        {
            "name": "idle",
            "path": "heroes/invoker/smd/idle.smd"
        }
    ],
    "attack": [
        {
            "name": "attack",
            "path": "heroes/invoker/smd/attack.smd"
        },
        {
            "name": "attack2",
            "path": "heroes/invoker/smd/attack2.smd"
        }
    ],
    "run": [
        {
            "name": "run",
            "path": "heroes/invoker/smd/run.smd"
        }
    ],
    "default": {
        "name": "idle",
        "path": "heroes/invoker/smd/idle.smd"
    }
}