{
    "accessors": {
        "attrbute_1": {
            "bufferView": "bufferView_37",
            "byteOffset": 0,
            "byteStride": 12,
            "count": 1802,
            "max": [
                72.38680267333984,
                86.9272689819336,
                361.6783142089844,
                0
            ],
            "min": [
                -71.5719985961914,
                -91.34429168701172,
                148.02684020996094,
                0
            ],
            "type": 35665
        },
        "attrbute_10": {
            "bufferView": "bufferView_37",
            "byteOffset": 123832,
            "byteStride": 16,
            "count": 491,
            "max": [
                1,
                1,
                2,
                -1
            ],
            "min": [
                0,
                -1,
                -1,
                -1
            ],
            "type": 35666
        },
        "attrbute_11": {
            "bufferView": "bufferView_37",
            "byteOffset": 131688,
            "byteStride": 12,
            "count": 491,
            "max": [
                1,
                0.800000011920929,
                0.3094930350780487
            ],
            "min": [
                0.09720396995544434,
                0,
                0
            ],
            "type": 35665
        },
        "attrbute_13": {
            "bufferView": "bufferView_37",
            "byteOffset": 137580,
            "byteStride": 12,
            "count": 278,
            "max": [
                58.741615295410156,
                -34.035301208496094,
                315.4442443847656,
                0
            ],
            "min": [
                -57.40046310424805,
                -82.6444320678711,
                269.0111999511719,
                0
            ],
            "type": 35665
        },
        "attrbute_14": {
            "bufferView": "bufferView_37",
            "byteOffset": 140916,
            "byteStride": 12,
            "count": 278,
            "max": [
                0.9997649788856506,
                0.9901931881904602,
                0.9770215153694153,
                0
            ],
            "min": [
                -0.9996767044067383,
                -0.9313635230064392,
                -0.9752333760261536,
                0
            ],
            "type": 35665
        },
        "attrbute_15": {
            "bufferView": "bufferView_37",
            "byteOffset": 144252,
            "byteStride": 8,
            "count": 278,
            "max": [
                1.5176876783370972,
                0.9812853336334229
            ],
            "min": [
                0.014140963554382324,
                0.026163816452026367
            ],
            "type": 35664
        },
        "attrbute_16": {
            "bufferView": "bufferView_37",
            "byteOffset": 146476,
            "byteStride": 16,
            "count": 278,
            "max": [
                0,
                -1,
                -1,
                -1
            ],
            "min": [
                0,
                -1,
                -1,
                -1
            ],
            "type": 35666
        },
        "attrbute_17": {
            "bufferView": "bufferView_37",
            "byteOffset": 150924,
            "byteStride": 12,
            "count": 278,
            "max": [
                1,
                0,
                0
            ],
            "min": [
                1,
                0,
                0
            ],
            "type": 35665
        },
        "attrbute_19": {
            "bufferView": "bufferView_37",
            "byteOffset": 154260,
            "byteStride": 12,
            "count": 770,
            "max": [
                42.2368049621582,
                56.278175354003906,
                286.8074645996094,
                0
            ],
            "min": [
                -41.42202377319336,
                -99.33744049072266,
                131.15069580078125,
                0
            ],
            "type": 35665
        },
        "attrbute_2": {
            "bufferView": "bufferView_37",
            "byteOffset": 21624,
            "byteStride": 12,
            "count": 1802,
            "max": [
                0.9986334443092346,
                0.999991238117218,
                0.9759201407432556,
                0
            ],
            "min": [
                -0.9989597797393799,
                -0.9987258315086365,
                -0.999945878982544,
                0
            ],
            "type": 35665
        },
        "attrbute_20": {
            "bufferView": "bufferView_37",
            "byteOffset": 163500,
            "byteStride": 12,
            "count": 770,
            "max": [
                0.9971873760223389,
                0.999798595905304,
                0.9986907839775085,
                0
            ],
            "min": [
                -0.9971874356269836,
                -0.9890247583389282,
                -0.9963805675506592,
                0
            ],
            "type": 35665
        },
        "attrbute_21": {
            "bufferView": "bufferView_37",
            "byteOffset": 172740,
            "byteStride": 8,
            "count": 770,
            "max": [
                0.9621449708938599,
                0.9924889802932739
            ],
            "min": [
                0.026332000270485878,
                0.013285994529724121
            ],
            "type": 35664
        },
        "attrbute_22": {
            "bufferView": "bufferView_37",
            "byteOffset": 178900,
            "byteStride": 16,
            "count": 770,
            "max": [
                17,
                18,
                19,
                -1
            ],
            "min": [
                0,
                -1,
                -1,
                -1
            ],
            "type": 35666
        },
        "attrbute_23": {
            "bufferView": "bufferView_37",
            "byteOffset": 191220,
            "byteStride": 12,
            "count": 770,
            "max": [
                1,
                0.9670436978340149,
                0.3410317003726959
            ],
            "min": [
                0.03295630216598511,
                0,
                0
            ],
            "type": 35665
        },
        "attrbute_25": {
            "bufferView": "bufferView_37",
            "byteOffset": 200460,
            "byteStride": 12,
            "count": 393,
            "max": [
                36.4652214050293,
                175.3468475341797,
                9.139416694641113,
                0
            ],
            "min": [
                -35.65047073364258,
                -134.10316467285156,
                -7.992825508117676,
                0
            ],
            "type": 35665
        },
        "attrbute_26": {
            "bufferView": "bufferView_37",
            "byteOffset": 205176,
            "byteStride": 12,
            "count": 393,
            "max": [
                0.9999998807907104,
                0.9999998807907104,
                0.9996780753135681,
                0
            ],
            "min": [
                -0.9999998807907104,
                -0.9999998807907104,
                -0.9996780753135681,
                0
            ],
            "type": 35665
        },
        "attrbute_27": {
            "bufferView": "bufferView_37",
            "byteOffset": 209892,
            "byteStride": 8,
            "count": 393,
            "max": [
                0.9817439913749695,
                0.9636310338973999
            ],
            "min": [
                0.02101999521255493,
                0.026576995849609375
            ],
            "type": 35664
        },
        "attrbute_28": {
            "bufferView": "bufferView_37",
            "byteOffset": 213036,
            "byteStride": 16,
            "count": 393,
            "max": [
                0,
                -1,
                -1,
                -1
            ],
            "min": [
                0,
                -1,
                -1,
                -1
            ],
            "type": 35666
        },
        "attrbute_29": {
            "bufferView": "bufferView_37",
            "byteOffset": 219324,
            "byteStride": 12,
            "count": 393,
            "max": [
                1,
                0,
                0
            ],
            "min": [
                1,
                0,
                0
            ],
            "type": 35665
        },
        "attrbute_3": {
            "bufferView": "bufferView_37",
            "byteOffset": 43248,
            "byteStride": 8,
            "count": 1802,
            "max": [
                0.991221010684967,
                0.9893720149993896
            ],
            "min": [
                0.017710000276565552,
                0.008404016494750977
            ],
            "type": 35664
        },
        "attrbute_31": {
            "bufferView": "bufferView_37",
            "byteOffset": 224040,
            "byteStride": 12,
            "count": 370,
            "max": [
                130.99142456054688,
                20.174169540405273,
                266.8434753417969,
                0
            ],
            "min": [
                -130.17666625976562,
                -61.85862350463867,
                180.3864288330078,
                0
            ],
            "type": 35665
        },
        "attrbute_32": {
            "bufferView": "bufferView_37",
            "byteOffset": 228480,
            "byteStride": 12,
            "count": 370,
            "max": [
                0.9354045391082764,
                0.995770275592804,
                0.952735185623169,
                0
            ],
            "min": [
                -0.9354045987129211,
                -0.9946012496948242,
                -0.9888484477996826,
                0
            ],
            "type": 35665
        },
        "attrbute_33": {
            "bufferView": "bufferView_37",
            "byteOffset": 232920,
            "byteStride": 8,
            "count": 370,
            "max": [
                0.9660600423812866,
                0.9779340028762817
            ],
            "min": [
                0.03468801826238632,
                0.03247201442718506
            ],
            "type": 35664
        },
        "attrbute_34": {
            "bufferView": "bufferView_37",
            "byteOffset": 235880,
            "byteStride": 16,
            "count": 370,
            "max": [
                4,
                4,
                4,
                -1
            ],
            "min": [
                0,
                -1,
                -1,
                -1
            ],
            "type": 35666
        },
        "attrbute_35": {
            "bufferView": "bufferView_37",
            "byteOffset": 241800,
            "byteStride": 12,
            "count": 370,
            "max": [
                1,
                0.9998040199279785,
                0.3496261537075043
            ],
            "min": [
                0.00019595245248638093,
                0,
                0
            ],
            "type": 35665
        },
        "attrbute_4": {
            "bufferView": "bufferView_37",
            "byteOffset": 57664,
            "byteStride": 16,
            "count": 1802,
            "max": [
                50,
                50,
                49,
                -1
            ],
            "min": [
                0,
                -1,
                -1,
                -1
            ],
            "type": 35666
        },
        "attrbute_5": {
            "bufferView": "bufferView_37",
            "byteOffset": 86496,
            "byteStride": 12,
            "count": 1802,
            "max": [
                1,
                0.9996262192726135,
                0.9985674023628235
            ],
            "min": [
                0.0003737840452231467,
                0,
                0
            ],
            "type": 35665
        },
        "attrbute_7": {
            "bufferView": "bufferView_37",
            "byteOffset": 108120,
            "byteStride": 12,
            "count": 491,
            "max": [
                17.221050262451172,
                -51.620574951171875,
                305.7508544921875,
                0
            ],
            "min": [
                -16.029813766479492,
                -97.77779388427734,
                255.2212677001953,
                0
            ],
            "type": 35665
        },
        "attrbute_8": {
            "bufferView": "bufferView_37",
            "byteOffset": 114012,
            "byteStride": 12,
            "count": 491,
            "max": [
                0.9863190054893494,
                0.9985656142234802,
                0.9943703413009644,
                0
            ],
            "min": [
                -0.9826182723045349,
                -0.994179368019104,
                -0.9985780119895935,
                0
            ],
            "type": 35665
        },
        "attrbute_9": {
            "bufferView": "bufferView_37",
            "byteOffset": 119904,
            "byteStride": 8,
            "count": 491,
            "max": [
                1.9890046119689941,
                0.9919822216033936
            ],
            "min": [
                0.016350984573364258,
                0.0144919753074646
            ],
            "type": 35664
        },
        "indices_12": {
            "bufferView": "bufferView_39",
            "byteOffset": 16200,
            "count": 1920,
            "type": 5123
        },
        "indices_18": {
            "bufferView": "bufferView_39",
            "byteOffset": 20040,
            "count": 1146,
            "type": 5123
        },
        "indices_24": {
            "bufferView": "bufferView_39",
            "byteOffset": 22332,
            "count": 4086,
            "type": 5123
        },
        "indices_30": {
            "bufferView": "bufferView_39",
            "byteOffset": 30504,
            "count": 2154,
            "type": 5123
        },
        "indices_36": {
            "bufferView": "bufferView_39",
            "byteOffset": 34812,
            "count": 2142,
            "type": 5123
        },
        "indices_6": {
            "bufferView": "bufferView_39",
            "byteOffset": 0,
            "count": 8100,
            "type": 5123
        }
    },
    "animations": {},
    "asset": {},
    "bufferViews": {
        "bufferView_37": {
            "buffer": "obsidian_destroyer.bin",
            "byteLength": 246240,
            "byteOffset": 0,
            "target": 34962
        },
        "bufferView_38": {
            "buffer": "obsidian_destroyer.bin",
            "byteLength": 6528,
            "byteOffset": 246240
        },
        "bufferView_39": {
            "buffer": "obsidian_destroyer.bin",
            "byteLength": 39096,
            "byteOffset": 252768,
            "target": 34963
        }
    },
    "buffers": {
        "obsidian_destroyer.bin": {
            "byteLength": 291864,
            "path": "obsidian_destroyer.bin"
        }
    },
    "cameras": {},
    "images": {
        "image_0": {
            "path": "textures/obsidian_body_color.png"
        },
        "image_1": {
            "path": "textures/obsidian_head_color.png"
        },
        "image_2": {
            "path": "textures/obsidian_horns_color.png"
        },
        "image_3": {
            "path": "textures/obsidian_rocks_color.png"
        },
        "image_4": {
            "path": "textures/obsidian_destroyer_weapon_color.png"
        },
        "image_5": {
            "path": "textures/obsidian_wings_color.png"
        }
    },
    "lights": {},
    "materials": {
        "Material #112": {
            "instanceTechnique": {
                "technique": "technique_0",
                "values": {
                    "ambient": [
                        0.5879999995231628,
                        0.5879999995231628,
                        0.5879999995231628
                    ],
                    "diffuse": "Map #22",
                    "emission": [
                        0,
                        0,
                        0
                    ],
                    "shininess": 2,
                    "specular": [
                        0.8999999761581421,
                        0.8999999761581421,
                        0.8999999761581421
                    ],
                    "transparency": 1
                }
            },
            "name": "Material #112"
        },
        "Material #123": {
            "instanceTechnique": {
                "technique": "technique_0",
                "values": {
                    "ambient": [
                        0.5879999995231628,
                        0.5879999995231628,
                        0.5879999995231628
                    ],
                    "diffuse": "Map #23",
                    "emission": [
                        0,
                        0,
                        0
                    ],
                    "shininess": 2,
                    "specular": [
                        0.8999999761581421,
                        0.8999999761581421,
                        0.8999999761581421
                    ],
                    "transparency": 1
                }
            },
            "name": "Material #123"
        },
        "Material #134": {
            "instanceTechnique": {
                "technique": "technique_0",
                "values": {
                    "ambient": [
                        0.5879999995231628,
                        0.5879999995231628,
                        0.5879999995231628
                    ],
                    "diffuse": "Map #24",
                    "emission": [
                        0,
                        0,
                        0
                    ],
                    "shininess": 2,
                    "specular": [
                        0.8999999761581421,
                        0.8999999761581421,
                        0.8999999761581421
                    ],
                    "transparency": 1
                }
            },
            "name": "Material #134"
        },
        "Material #145": {
            "instanceTechnique": {
                "technique": "technique_0",
                "values": {
                    "ambient": [
                        0.5879999995231628,
                        0.5879999995231628,
                        0.5879999995231628
                    ],
                    "diffuse": "Map #25",
                    "emission": [
                        0,
                        0,
                        0
                    ],
                    "shininess": 2,
                    "specular": [
                        0.8999999761581421,
                        0.8999999761581421,
                        0.8999999761581421
                    ],
                    "transparency": 1
                }
            },
            "name": "Material #145"
        },
        "Material #156": {
            "instanceTechnique": {
                "technique": "technique_0",
                "values": {
                    "ambient": [
                        0.5879999995231628,
                        0.5879999995231628,
                        0.5879999995231628
                    ],
                    "diffuse": "Map #26",
                    "emission": [
                        0,
                        0,
                        0
                    ],
                    "shininess": 2,
                    "specular": [
                        0.8999999761581421,
                        0.8999999761581421,
                        0.8999999761581421
                    ],
                    "transparency": 1
                }
            },
            "name": "Material #156"
        },
        "Material #167": {
            "instanceTechnique": {
                "technique": "technique_0",
                "values": {
                    "ambient": [
                        0.5879999995231628,
                        0.5879999995231628,
                        0.5879999995231628
                    ],
                    "diffuse": "Map #27",
                    "emission": [
                        0,
                        0,
                        0
                    ],
                    "shininess": 2,
                    "specular": [
                        0.8999999761581421,
                        0.8999999761581421,
                        0.8999999761581421
                    ],
                    "transparency": 1
                }
            },
            "name": "Material #167"
        }
    },
    "meshes": {
        "obsidian_destroyer_head_model_LOD0-mesh": {
            "name": "obsidian_destroyer_head_model_LOD0-mesh",
            "primitives": [
                {
                    "attributes": {
                        "JOINT": "attrbute_10",
                        "NORMAL": "attrbute_8",
                        "POSITION": "attrbute_7",
                        "TEXCOORD_0": "attrbute_9",
                        "WEIGHT": "attrbute_11"
                    },
                    "indices": "indices_12",
                    "material": "Material #123"
                }
            ]
        },
        "obsidian_destroyer_horns_model_LOD0-mesh": {
            "name": "obsidian_destroyer_horns_model_LOD0-mesh",
            "primitives": [
                {
                    "attributes": {
                        "JOINT": "attrbute_16",
                        "NORMAL": "attrbute_14",
                        "POSITION": "attrbute_13",
                        "TEXCOORD_0": "attrbute_15",
                        "WEIGHT": "attrbute_17"
                    },
                    "indices": "indices_18",
                    "material": "Material #134"
                }
            ]
        },
        "obsidian_destroyer_model_LOD0-mesh": {
            "name": "obsidian_destroyer_model_LOD0-mesh",
            "primitives": [
                {
                    "attributes": {
                        "JOINT": "attrbute_4",
                        "NORMAL": "attrbute_2",
                        "POSITION": "attrbute_1",
                        "TEXCOORD_0": "attrbute_3",
                        "WEIGHT": "attrbute_5"
                    },
                    "indices": "indices_6",
                    "material": "Material #112"
                }
            ]
        },
        "obsidian_destroyer_rocks_model_LOD0-mesh": {
            "name": "obsidian_destroyer_rocks_model_LOD0-mesh",
            "primitives": [
                {
                    "attributes": {
                        "JOINT": "attrbute_22",
                        "NORMAL": "attrbute_20",
                        "POSITION": "attrbute_19",
                        "TEXCOORD_0": "attrbute_21",
                        "WEIGHT": "attrbute_23"
                    },
                    "indices": "indices_24",
                    "material": "Material #145"
                }
            ]
        },
        "obsidian_destroyer_weapon_model_LOD0-mesh": {
            "name": "obsidian_destroyer_weapon_model_LOD0-mesh",
            "primitives": [
                {
                    "attributes": {
                        "JOINT": "attrbute_28",
                        "NORMAL": "attrbute_26",
                        "POSITION": "attrbute_25",
                        "TEXCOORD_0": "attrbute_27",
                        "WEIGHT": "attrbute_29"
                    },
                    "indices": "indices_30",
                    "material": "Material #156"
                }
            ]
        },
        "obsidian_destroyer_wings_model_LOD0-mesh": {
            "name": "obsidian_destroyer_wings_model_LOD0-mesh",
            "primitives": [
                {
                    "attributes": {
                        "JOINT": "attrbute_34",
                        "NORMAL": "attrbute_32",
                        "POSITION": "attrbute_31",
                        "TEXCOORD_0": "attrbute_33",
                        "WEIGHT": "attrbute_35"
                    },
                    "indices": "indices_36",
                    "material": "Material #167"
                }
            ]
        }
    },
    "nodes": {
        "Head_0": {
            "children": [
                "Head_1"
            ],
            "jointId": "Head_0",
            "matrix": [
                0.9740872383117679,
                -4.6448093371509474e-7,
                0.22617346048355108,
                0,
                -4.095243659736215e-8,
                1,
                0.0000022300237105804836,
                0,
                -0.2261734604845381,
                -0.0000021814999919090924,
                0.9740872383115385,
                0,
                19.905410766601534,
                2.3841857904605135e-7,
                0.24106979370115056,
                1
            ],
            "name": "Head_0"
        },
        "Head_1": {
            "children": [
                "jaw3_0"
            ],
            "jointId": "Head_1",
            "matrix": [
                -0.17840145528316537,
                -0.0000022543140402622324,
                -0.9839577078819273,
                0,
                -6.719022832165393e-7,
                0.9999999999999998,
                -0.0000021692453629159932,
                0,
                0.983957707881817,
                2.741269009025156e-7,
                -0.17840145528377346,
                0,
                20.840133666992216,
                0.000011086463928222656,
                -0.00000762939453125,
                1
            ],
            "name": "Head_1"
        },
        "Index1_0_A_L": {
            "children": [],
            "jointId": "Index1_0_A_L",
            "matrix": [
                0.9999999999999994,
                -2.2351741790771167e-8,
                2.98023223876953e-8,
                0,
                2.2351741124637458e-8,
                0.9999999999999998,
                2.235174356712857e-8,
                0,
                -2.9802326440010014e-8,
                -2.2351745565530436e-8,
                1.0000001192093009,
                0,
                20.928802490234375,
                -3.5721893310547017,
                3.6087188720703125,
                1
            ],
            "name": "Index1_0_A_L"
        },
        "Index1_0_A_R": {
            "children": [],
            "jointId": "Index1_0_A_R",
            "matrix": [
                0.999999940395355,
                -3.3644106167684936e-8,
                -4.768371582031248e-7,
                0,
                3.3644106396682775e-8,
                1.0000000000000056,
                -3.725270758536711e-9,
                0,
                4.768371867501696e-7,
                3.725254715775679e-9,
                1.0000000000000018,
                0,
                -20.928817749023438,
                3.5721588134765625,
                -3.6087493896484375,
                1
            ],
            "name": "Index1_0_A_R"
        },
        "Mid1_0_A_L": {
            "children": [],
            "jointId": "Mid1_0_A_L",
            "matrix": [
                0.9999999999999994,
                -2.2351741790771167e-8,
                2.98023223876953e-8,
                0,
                2.2351741124637458e-8,
                0.9999999999999998,
                2.235174356712857e-8,
                0,
                -2.9802326440010014e-8,
                -2.2351745565530436e-8,
                1.0000001192093009,
                0,
                6.151275634765639,
                -13.30410766601564,
                7.7529144287109375,
                1
            ],
            "name": "Mid1_0_A_L"
        },
        "Mid1_0_A_R": {
            "children": [],
            "jointId": "Mid1_0_A_R",
            "matrix": [
                0.999999940395355,
                -3.3644106167684936e-8,
                -4.768371582031248e-7,
                0,
                3.3644106396682775e-8,
                1.0000000000000056,
                -3.725270758536711e-9,
                0,
                4.768371867501696e-7,
                3.725254715775679e-9,
                1.0000000000000018,
                0,
                -6.1512908935546875,
                13.304084777832031,
                -7.752912521362308,
                1
            ],
            "name": "Mid1_0_A_R"
        },
        "RWeapon": {
            "children": [],
            "jointId": "RWeapon",
            "matrix": [
                0.28266066312789906,
                -0.8164587020874022,
                0.5034844279289244,
                0,
                0.6525212719870152,
                0.5483937573328271,
                0.5229531347830545,
                0,
                -0.7030776980795231,
                0.180716107692872,
                0.6877663496510119,
                0,
                -30.434446334838842,
                -184.33604431152344,
                -156.33557128906247,
                1
            ],
            "name": "RWeapon"
        },
        "Ring4_0": {
            "children": [],
            "jointId": "Ring4_0",
            "matrix": [
                0.9545729160308833,
                -0.18106126785278318,
                -0.23665872216224673,
                0,
                -0.2412245953601258,
                -0.0033011540107381466,
                -0.9704639329678675,
                0,
                0.17493216385725197,
                0.9834663820380536,
                -0.046827618100602375,
                0,
                17.578956604003906,
                -3.334342956542983,
                -4.358213424682617,
                1
            ],
            "name": "Ring4_0"
        },
        "Ring5_0": {
            "children": [],
            "jointId": "Ring5_0",
            "matrix": [
                -0.954573214054108,
                0.18106067180633542,
                0.2366581857204438,
                0,
                -0.24122398435190615,
                -0.0033012836464355374,
                -0.9704638811276496,
                0,
                -0.1749315319700537,
                -0.9834662625915424,
                0.046827484364805765,
                0,
                -17.578956604003906,
                3.3343048095703267,
                4.358188629150391,
                1
            ],
            "name": "Ring5_0"
        },
        "Root_0": {
            "children": [
                "WingBase1_0_R",
                "clavicle_A_R",
                "Spine_0",
                "WingBase0_0_L",
                "clavicle_A_L",
                "Spine0_0"
            ],
            "jointId": "Root_0",
            "matrix": [
                -1.629206851037603e-7,
                -1.0000000000000002,
                0,
                0,
                1.0000000000000002,
                -1.629206851037603e-7,
                0,
                0,
                0,
                0,
                1,
                0,
                0.40738528966903687,
                -60.538143157958984,
                174.68795776367188,
                1
            ],
            "name": "Root_0"
        },
        "Spine0_0": {
            "children": [
                "Spine0_1"
            ],
            "jointId": "Spine0_0",
            "matrix": [
                -0.9847639203071596,
                -3.208768358607731e-7,
                -0.1738966703414917,
                0,
                3.0382777583531744e-8,
                -1,
                0.000001673160113568728,
                0,
                -0.17389667034201076,
                0.0000016423842488818407,
                0.9847639203070676,
                0,
                -33.43538665771484,
                -0.000005722045898493011,
                -5.948883056640625,
                1
            ],
            "name": "Spine0_0"
        },
        "Spine0_1": {
            "children": [
                "thigh_R",
                "Spine0_2",
                "thigh_L"
            ],
            "jointId": "Spine0_1",
            "matrix": [
                0.9998567700386046,
                5.293955920339377e-23,
                -0.016928270459175027,
                0,
                1.9247972458241985e-15,
                0.9999999999999997,
                1.1368683750985779e-13,
                0,
                0.016928270459175082,
                -1.1370313738837828e-13,
                0.9998567700386046,
                0,
                31.200912475585934,
                -0.0000029206275939941406,
                0,
                1
            ],
            "name": "Spine0_1"
        },
        "Spine0_2": {
            "children": [],
            "jointId": "Spine0_2",
            "matrix": [
                1.0000002384185793,
                0,
                -2.980232241545089e-8,
                0,
                6.829203137237796e-21,
                0.9999999999999999,
                2.2737367586674853e-13,
                0,
                2.9802322443206464e-8,
                -2.2737373007685716e-13,
                1.0000002384185793,
                0,
                28.14922523498535,
                -0.0000028312206267755435,
                0.00001525878909092171,
                1
            ],
            "name": "Spine0_2"
        },
        "Spine_0": {
            "children": [
                "Spine_1"
            ],
            "jointId": "Spine_0",
            "matrix": [
                0.1117625012993823,
                1.820838591015689e-8,
                0.9937349557876589,
                0,
                -1.6292035072999507e-7,
                1.0000000000000002,
                -3.2879931264554395e-24,
                0,
                -0.9937349557876587,
                -1.6189964752958147e-7,
                0.11176250129938521,
                0,
                14.690006256103516,
                0.000003159046173095703,
                18.683120727539062,
                1
            ],
            "name": "Spine_0"
        },
        "Spine_1": {
            "children": [
                "Spine_3"
            ],
            "jointId": "Spine_1",
            "matrix": [
                0.9626286029815677,
                1.3625473633486222e-15,
                0.27082505822181707,
                0,
                -2.0165945829053825e-15,
                1,
                2.13674564153442e-15,
                0,
                -0.2708250582218171,
                -2.603036817162511e-15,
                0.9626286029815676,
                0,
                24.467178344726562,
                0.000001043081283569336,
                0.0000152587890625,
                1
            ],
            "name": "Spine_1"
        },
        "Spine_3": {
            "children": [
                "clavicle_R",
                "Head_0",
                "clavicle_L"
            ],
            "jointId": "Spine_3",
            "matrix": [
                0.977813720703125,
                6.276710650798122e-15,
                -0.20947661995887754,
                0,
                -6.025713817964694e-15,
                1,
                1.836410204811132e-15,
                0,
                0.20947661995887756,
                -5.334209316768498e-16,
                0.9778137207031251,
                0,
                23.134796142578125,
                0.0000010430812835138248,
                -0.00000762939453125,
                1
            ],
            "name": "Spine_3"
        },
        "WingBase0_0_L": {
            "children": [
                "WingBend1_0"
            ],
            "jointId": "WingBase0_0_L",
            "matrix": [
                0.02979996614158161,
                0.7872744202613833,
                0.6158819794654846,
                0,
                -0.038048778253596156,
                0.6166026788887878,
                -0.7863546594924223,
                0,
                -0.9988316299348147,
                -2.1463897114803435e-7,
                0.048329580545290046,
                0,
                -19.925247192382812,
                25.351364135742184,
                14.108306884765625,
                1
            ],
            "name": "WingBase0_0_L"
        },
        "WingBase1_0_R": {
            "children": [
                "WingBend2_0"
            ],
            "jointId": "WingBase1_0_R",
            "matrix": [
                -0.02980552613735206,
                0.787275493144989,
                -0.6158805489540101,
                0,
                -0.038055008647019675,
                -0.6166013688674413,
                -0.7863552405034123,
                0,
                -0.9988310337558429,
                -3.9205810565588587e-7,
                0.04833790558287746,
                0,
                -19.92523956298828,
                -25.351369857788082,
                14.108306884765625,
                1
            ],
            "name": "WingBase1_0_R"
        },
        "WingBend1_0": {
            "children": [],
            "jointId": "WingBend1_0",
            "matrix": [
                1.0000002384185787,
                -1.1102230246251565e-16,
                -1.583248376811619e-7,
                0,
                1.815214645262131e-14,
                0.9999997615814282,
                1.1548399923844155e-7,
                0,
                1.5832477162636138e-7,
                -1.1548400614264098e-7,
                0.9999998211860627,
                0,
                46.98065185546872,
                0.631866455078125,
                16.587766647338867,
                1
            ],
            "name": "WingBend1_0"
        },
        "WingBend2_0": {
            "children": [],
            "jointId": "WingBend2_0",
            "matrix": [
                0.9999998807907103,
                2.9802322165650708e-8,
                -1.6391277312191588e-7,
                0,
                -2.9802326606542806e-8,
                0.9999999999999999,
                -3.72529029152302e-9,
                0,
                1.639127925577577e-7,
                3.725295183443222e-9,
                0.9999999999999993,
                0,
                -46.9801025390625,
                0.6319885253905966,
                16.587770462036133,
                1
            ],
            "name": "WingBend2_0"
        },
        "ankle_L": {
            "children": [
                "toeBall_L"
            ],
            "jointId": "ankle_L",
            "matrix": [
                0.7335984706878661,
                -0.16117122769355777,
                0.6601951122283937,
                0,
                0.1198010411973469,
                0.986926459050412,
                0.10781401909955203,
                0,
                -0.6689405693953174,
                -1.3769178846406716e-7,
                0.7433162521320696,
                0,
                19.473068237304673,
                -0.0000038146972585195726,
                0.00002288818359375,
                1
            ],
            "name": "ankle_L"
        },
        "ankle_R": {
            "children": [
                "toeBall_R"
            ],
            "jointId": "ankle_R",
            "matrix": [
                0.7335981130599973,
                -0.16117109358310694,
                0.6601954102516174,
                0,
                0.11980134017489624,
                0.9869262945366286,
                0.10781346246394163,
                0,
                -0.6689406175189107,
                5.422994418143035e-7,
                0.743315773699525,
                0,
                -19.473056793212898,
                -0.000011444091796875,
                0,
                1
            ],
            "name": "ankle_R"
        },
        "bicep_A_L": {
            "children": [
                "elbow_A_L"
            ],
            "jointId": "bicep_A_L",
            "matrix": [
                0.15258768200874312,
                -0.9167828559875492,
                0.369088411331177,
                0,
                -0.4944761661342838,
                -0.39417599283996246,
                -0.7746729826800063,
                0,
                0.855692924340277,
                -0.06429988467786972,
                -0.5134738071766832,
                0,
                21.607364654541012,
                0.0000152587890625,
                -0.000022888183579539145,
                1
            ],
            "name": "bicep_A_L"
        },
        "bicep_A_R": {
            "children": [
                "elbow_A_R"
            ],
            "jointId": "bicep_A_R",
            "matrix": [
                0.15258733928203583,
                -0.9167832732200624,
                0.36908808350563055,
                0,
                -0.4944760977433973,
                -0.3941755036455551,
                -0.7746733886566887,
                0,
                0.8556928117628517,
                -0.0642998634504448,
                -0.5134734420881626,
                0,
                -21.60735702514648,
                0.00004577636721592171,
                -0.0000076293945028282906,
                1
            ],
            "name": "bicep_A_R"
        },
        "bicep_L": {
            "children": [
                "elbow_L"
            ],
            "jointId": "bicep_L",
            "matrix": [
                0.4377923607826234,
                -0.31296858191490173,
                -0.8428453207015991,
                0,
                -0.7427626822536149,
                0.40232378578839495,
                -0.5351996645106561,
                0,
                0.5065975749572585,
                0.8603406723577339,
                -0.05632712280434062,
                0,
                28.564964294433594,
                0.00006103515625,
                0.000030517578125,
                1
            ],
            "name": "bicep_L"
        },
        "bicep_R": {
            "children": [
                "elbow_R"
            ],
            "jointId": "bicep_R",
            "matrix": [
                0.43779194355010986,
                -0.31296882033348083,
                -0.8428460359573366,
                0,
                -0.7427632558697477,
                0.4023245008668871,
                -0.535199519921838,
                0,
                0.5065981246013671,
                0.860340681831206,
                -0.05632728717246408,
                0,
                -28.564939498901364,
                -0.000022888183607960855,
                0.0000152587890625,
                1
            ],
            "name": "bicep_R"
        },
        "clavicle_A_L": {
            "children": [
                "bicep_A_L"
            ],
            "jointId": "clavicle_A_L",
            "matrix": [
                -0.04044179245829592,
                0.9946001768112185,
                0.09557560086250307,
                0,
                0.003883189058464148,
                -0.09549669557034354,
                0.9954221848105044,
                0,
                0.9991743558336852,
                0.04062780044427568,
                -1.629814506284424e-7,
                0,
                5.35894393920897,
                6.03204870223999,
                -14.683853149414062,
                1
            ],
            "name": "clavicle_A_L"
        },
        "clavicle_A_R": {
            "children": [
                "bicep_A_R"
            ],
            "jointId": "clavicle_A_R",
            "matrix": [
                0.04044099897146229,
                0.9946002960205078,
                -0.09557554870843886,
                0,
                -0.003882783584374851,
                -0.09549665150691386,
                -0.995422184756818,
                0,
                -0.9991742965810271,
                0.040626964773423806,
                -1.6228295862024414e-7,
                0,
                5.35894393920897,
                -6.032048225402831,
                -14.683853149414062,
                1
            ],
            "name": "clavicle_A_R"
        },
        "clavicle_L": {
            "children": [
                "bicep_L"
            ],
            "jointId": "clavicle_L",
            "matrix": [
                0.2243123650550842,
                0.9144291877746583,
                0.33690243959426885,
                0,
                -0.08026359126934819,
                -0.3272018086585481,
                0.9415396353243667,
                0,
                0.9712064134976818,
                -0.23823998257628157,
                -4.0978192894502996e-8,
                0,
                -0.384429931640625,
                1.4000000953674316,
                -7.4308624267578125,
                1
            ],
            "name": "clavicle_L"
        },
        "clavicle_R": {
            "children": [
                "bicep_R"
            ],
            "jointId": "clavicle_R",
            "matrix": [
                -0.22431275248527519,
                0.9144290685653687,
                -0.33690264821052546,
                0,
                0.08026381003488894,
                -0.3272019764266009,
                -0.9415396298463867,
                0,
                -0.9712063560921748,
                -0.2382404206460505,
                1.4901160846902961e-8,
                0,
                -0.384429931640625,
                -1.399999976158142,
                -7.4308624267578125,
                1
            ],
            "name": "clavicle_R"
        },
        "elbow_A_L": {
            "children": [
                "wrist_A_L"
            ],
            "jointId": "elbow_A_L",
            "matrix": [
                0.857686221599579,
                -1.1920928966180355e-7,
                -0.5141735672950746,
                0,
                -9.94122432707023e-8,
                1.0000002384186186,
                -3.9767471987639524e-7,
                0,
                0.5141735778228275,
                3.9219519015754045e-7,
                0.8576862391606954,
                0,
                34.184791564941406,
                0,
                -0.0000133514404296875,
                1
            ],
            "name": "elbow_A_L"
        },
        "elbow_A_R": {
            "children": [
                "wrist_A_R"
            ],
            "jointId": "elbow_A_R",
            "matrix": [
                0.8576860427856446,
                -5.066394806463315e-7,
                -0.5141740441322327,
                0,
                3.327620968218703e-7,
                1.0000002384185258,
                -4.302710293700024e-7,
                0,
                0.5141740441323144,
                1.9793977631965554e-7,
                0.857686042785586,
                0,
                -34.18475341796875,
                0.00001525878903407829,
                -0.000001907348641694284,
                1
            ],
            "name": "elbow_A_R"
        },
        "elbow_L": {
            "children": [
                "wrist_L"
            ],
            "jointId": "elbow_L",
            "matrix": [
                0.6001511216163635,
                2.682209014892578e-7,
                -0.7998867630958554,
                0,
                3.1025581798127533e-7,
                1.000000357627856,
                5.68107131563439e-7,
                0,
                0.7998867153470576,
                -5.891194083673668e-7,
                0.6001510857904765,
                0,
                34.83757019042969,
                -0.0000457763671875,
                0.00005340576174006628,
                1
            ],
            "name": "elbow_L"
        },
        "elbow_R": {
            "children": [
                "wrist_R"
            ],
            "jointId": "elbow_R",
            "matrix": [
                0.6001510620117188,
                -2.6822090143374666e-7,
                -0.7998866438865659,
                0,
                3.00451692247794e-7,
                0.9999996423721611,
                -1.0989607593381301e-7,
                0,
                0.7998866534094425,
                -1.7437311350398943e-7,
                0.6001510691567455,
                0,
                -34.837524414062486,
                -0.00003051757815342171,
                0.00003051757813210543,
                1
            ],
            "name": "elbow_R"
        },
        "index_0_L": {
            "children": [
                "index_1_L"
            ],
            "jointId": "index_0_L",
            "matrix": [
                0.9093129634857179,
                0.38352137804031355,
                -0.16143685579299938,
                0,
                0.22308912589584262,
                -0.12182711043562061,
                0.9671554376223122,
                0,
                0.35125722037261475,
                -0.9154613145777457,
                -0.19633831909683797,
                0,
                18.62413787841797,
                3.311859130859375,
                -5.42864990234375,
                1
            ],
            "name": "index_0_L"
        },
        "index_0_R": {
            "children": [
                "index_1_R"
            ],
            "jointId": "index_0_R",
            "matrix": [
                0.9093124866485596,
                0.383521616458893,
                -0.1614364087581634,
                0,
                0.22308908337115424,
                -0.12182793559093996,
                0.9671550770841182,
                0,
                0.3512573463963966,
                -0.9154607120628901,
                -0.196339111068611,
                0,
                -18.6240997314453,
                -3.3118896484375,
                5.42864990234375,
                1
            ],
            "name": "index_0_R"
        },
        "index_1_L": {
            "children": [],
            "jointId": "index_1_L",
            "matrix": [
                0.9999997615814209,
                -5.960464477539063e-8,
                -4.172325134832455e-7,
                0,
                5.960483923095339e-8,
                1.0000000000000018,
                4.321336746493376e-7,
                0,
                4.1723258709103206e-7,
                -4.321336993517999e-7,
                0.9999999999999915,
                0,
                11.105560302734375,
                -0.000030517578125,
                -2.842170943040401e-14,
                1
            ],
            "name": "index_1_L"
        },
        "index_1_R": {
            "children": [],
            "jointId": "index_1_R",
            "matrix": [
                1.0000002384185787,
                3.278255462091373e-7,
                5.551115123125783e-17,
                0,
                -3.2782546804943635e-7,
                1.000000000000046,
                -4.0233135220613114e-7,
                0,
                -1.3183898417423734e-13,
                4.0233149606327956e-7,
                1.000000357627902,
                0,
                -11.10567474365233,
                -0.00006103515625,
                -2.842170943040401e-14,
                1
            ],
            "name": "index_1_R"
        },
        "jaw3_0": {
            "children": [],
            "jointId": "jaw3_0",
            "matrix": [
                0.99999988079071,
                2.778628171995478e-8,
                -1.0587911840678754e-22,
                0,
                -2.7786285032338063e-8,
                0.9999999999999999,
                1.6540433023237703e-7,
                0,
                4.595971390346476e-15,
                -1.6540431051464428e-7,
                0.9999998807907099,
                0,
                0.5569610595703267,
                0.0000016987323760431217,
                -8.453582763671875,
                1
            ],
            "name": "jaw3_0"
        },
        "knee_L": {
            "children": [
                "ankle_L"
            ],
            "jointId": "knee_L",
            "matrix": [
                0.35794997215270974,
                7.450580596923828e-8,
                -0.9337403178215028,
                0,
                -1.8871041881918238e-7,
                0.9999998807906927,
                7.450580985501887e-9,
                0,
                0.933740607542227,
                1.7353966579036761e-7,
                0.357950083217356,
                0,
                32.322410583496065,
                0.0000152587890625,
                -0.0000152587890625,
                1
            ],
            "name": "knee_L"
        },
        "knee_R": {
            "children": [
                "ankle_R"
            ],
            "jointId": "knee_R",
            "matrix": [
                0.3579501211643221,
                -2.0116567607531e-7,
                -0.9337407350540162,
                0,
                5.231225720936372e-7,
                0.9999997019767461,
                -1.4901168569891876e-8,
                0,
                0.9337409650092867,
                -4.83127242892345e-7,
                0.3579502093179291,
                0,
                -32.32244110107422,
                -0.000019073486328125,
                -0.000015258789069605427,
                1
            ],
            "name": "knee_R"
        },
        "obsidian_destroyer_head_model_LOD0": {
            "children": [],
            "instanceSkin": {
                "skeletons": [
                    "Root_0"
                ],
                "skin": "skin_1",
                "sources": [
                    "obsidian_destroyer_head_model_LOD0-mesh"
                ]
            },
            "matrix": [
                1,
                0,
                0,
                0,
                0,
                1,
                0,
                0,
                0,
                0,
                1,
                0,
                0,
                0,
                0,
                1
            ],
            "name": "obsidian_destroyer_head_model_LOD0"
        },
        "obsidian_destroyer_horns_model_LOD0": {
            "children": [],
            "instanceSkin": {
                "skeletons": [
                    "Root_0"
                ],
                "skin": "skin_2",
                "sources": [
                    "obsidian_destroyer_horns_model_LOD0-mesh"
                ]
            },
            "matrix": [
                1,
                0,
                0,
                0,
                0,
                1,
                0,
                0,
                0,
                0,
                1,
                0,
                0,
                0,
                0,
                1
            ],
            "name": "obsidian_destroyer_horns_model_LOD0"
        },
        "obsidian_destroyer_model_LOD0": {
            "children": [],
            "instanceSkin": {
                "skeletons": [
                    "Root_0"
                ],
                "skin": "skin_0",
                "sources": [
                    "obsidian_destroyer_model_LOD0-mesh"
                ]
            },
            "matrix": [
                1,
                0,
                0,
                0,
                0,
                1,
                0,
                0,
                0,
                0,
                1,
                0,
                0,
                0,
                0,
                1
            ],
            "name": "obsidian_destroyer_model_LOD0"
        },
        "obsidian_destroyer_rocks_model_LOD0": {
            "children": [],
            "instanceSkin": {
                "skeletons": [
                    "Root_0"
                ],
                "skin": "skin_3",
                "sources": [
                    "obsidian_destroyer_rocks_model_LOD0-mesh"
                ]
            },
            "matrix": [
                1,
                0,
                0,
                0,
                0,
                1,
                0,
                0,
                0,
                0,
                1,
                0,
                0,
                0,
                0,
                1
            ],
            "name": "obsidian_destroyer_rocks_model_LOD0"
        },
        "obsidian_destroyer_weapon_model_LOD0": {
            "children": [],
            "instanceSkin": {
                "skeletons": [
                    "Root_0"
                ],
                "skin": "skin_4",
                "sources": [
                    "obsidian_destroyer_weapon_model_LOD0-mesh"
                ]
            },
            "matrix": [
                1,
                0,
                0,
                0,
                0,
                1,
                0,
                0,
                0,
                0,
                1,
                0,
                0,
                0,
                0,
                1
            ],
            "name": "obsidian_destroyer_weapon_model_LOD0"
        },
        "obsidian_destroyer_wings_model_LOD0": {
            "children": [],
            "instanceSkin": {
                "skeletons": [
                    "Root_0"
                ],
                "skin": "skin_5",
                "sources": [
                    "obsidian_destroyer_wings_model_LOD0-mesh"
                ]
            },
            "matrix": [
                1,
                0,
                0,
                0,
                0,
                1,
                0,
                0,
                0,
                0,
                1,
                0,
                0,
                0,
                0,
                1
            ],
            "name": "obsidian_destroyer_wings_model_LOD0"
        },
        "thigh_L": {
            "children": [
                "knee_L"
            ],
            "jointId": "thigh_L",
            "matrix": [
                -0.04871509969234453,
                -0.2308997362852092,
                -0.9717574119567873,
                0,
                0.2913429303021385,
                -0.9338885417672959,
                0.2072964050913529,
                0,
                -0.9553776872216772,
                -0.2730161553391795,
                0.11276546615230426,
                0,
                5.53166389465332,
                -15.478665351867678,
                -10.493545532226562,
                1
            ],
            "name": "thigh_L"
        },
        "thigh_R": {
            "children": [
                "knee_R"
            ],
            "jointId": "thigh_R",
            "matrix": [
                0.04871493577957145,
                -0.23089960217475855,
                0.9717574715614319,
                0,
                -0.29134459208500335,
                -0.9338881046019308,
                -0.20729612545350443,
                0,
                0.9553770728380082,
                -0.27301779147254446,
                -0.11276561836992563,
                0,
                5.531671524047852,
                15.478660583496099,
                -10.493545532226562,
                1
            ],
            "name": "thigh_R"
        },
        "thumb_0_L": {
            "children": [
                "thumb_1_L"
            ],
            "jointId": "thumb_0_L",
            "matrix": [
                0.7584455609321593,
                0.5260595083236694,
                -0.3847362697124482,
                0,
                0.499127837898477,
                -0.8484374299080408,
                -0.17613957810555458,
                0,
                -0.41908455396954003,
                -0.05844030165752223,
                -0.9060645522976436,
                0,
                7.780967712402358,
                10.984054565429688,
                -11.850677490234375,
                1
            ],
            "name": "thumb_0_L"
        },
        "thumb_0_R": {
            "children": [
                "thumb_1_R"
            ],
            "jointId": "thumb_0_R",
            "matrix": [
                0.7584455013275146,
                0.5260596275329591,
                -0.38473543524742126,
                0,
                0.4991280678541755,
                -0.8484373146451444,
                -0.17613968942947442,
                0,
                -0.4190839688292354,
                -0.05843991191111075,
                -0.9060647842480429,
                0,
                -7.781013488769503,
                -10.984054565429688,
                11.85064697265625,
                1
            ],
            "name": "thumb_0_R"
        },
        "thumb_1_L": {
            "children": [],
            "jointId": "thumb_1_L",
            "matrix": [
                1.000000238418579,
                -5.215406417569124e-7,
                7.748603819135447e-7,
                0,
                5.215407226089042e-7,
                1.000000238418612,
                -1.0430812841244474e-7,
                0,
                -7.748602353085943e-7,
                1.0430852012688341e-7,
                1.000000119209592,
                0,
                8.531997680664048,
                -0.00003051757809657829,
                -0.00007629394528407829,
                1
            ],
            "name": "thumb_1_L"
        },
        "thumb_1_R": {
            "children": [],
            "jointId": "thumb_1_R",
            "matrix": [
                1.0000001192092896,
                -1.7881393421514957e-7,
                -2.9802322498717615e-8,
                0,
                1.7881389210994136e-7,
                0.9999998807907076,
                1.4901161082825354e-8,
                0,
                2.980231600391292e-8,
                -1.4901168299275014e-8,
                1.0000000000000009,
                0,
                -8.531959533691435,
                -0.0000152587890625,
                0.0000457763671875,
                1
            ],
            "name": "thumb_1_R"
        },
        "toeBall_L": {
            "children": [],
            "jointId": "toeBall_L",
            "matrix": [
                0.15389476716518385,
                0.35494890809059115,
                -0.9221321344375614,
                0,
                -0.07004252303644552,
                0.9348209054152592,
                0.3481436877360941,
                0,
                0.9856016045175777,
                0.011010969346952388,
                0.1687255602327337,
                0,
                20.716178894042983,
                0.00011444091796875,
                0.00002288818359375,
                1
            ],
            "name": "toeBall_L"
        },
        "toeBall_R": {
            "children": [],
            "jointId": "toeBall_R",
            "matrix": [
                0.15389454364776603,
                0.35494902729988104,
                -0.9221321344375609,
                0,
                -0.07004199255837429,
                0.9348209852701532,
                0.34814394483282574,
                0,
                0.9856017188435897,
                0.011010517397940825,
                0.16872516786897715,
                0,
                -20.71619415283203,
                -0.00000762939453125,
                0.000015258789058947286,
                1
            ],
            "name": "toeBall_R"
        },
        "wrist_A_L": {
            "children": [
                "Ring4_0",
                "Index1_0_A_L",
                "Mid1_0_A_L"
            ],
            "jointId": "wrist_A_L",
            "matrix": [
                0.7793456315994265,
                0.4396306574344636,
                0.44648122787475586,
                0,
                0.5896725045048603,
                -0.7555672045978766,
                -0.2853158780565927,
                0,
                0.21191289869658955,
                0.4856372323385104,
                -0.8480858409406841,
                0,
                38.260677337646484,
                2.842170943040401e-14,
                -0.000015258789069605427,
                1
            ],
            "name": "wrist_A_L"
        },
        "wrist_A_R": {
            "children": [
                "Mid1_0_A_R",
                "Ring5_0",
                "Index1_0_A_R"
            ],
            "jointId": "wrist_A_R",
            "matrix": [
                0.7793446779251098,
                0.4396311342716218,
                0.4464818239212036,
                0,
                0.5896728898490375,
                -0.7555666485224788,
                -0.28531465087211144,
                0,
                0.21191366115783777,
                0.48563688698639623,
                -0.8480857656140129,
                0,
                -38.26065063476561,
                -0.0000152587890625,
                0.000003814697265625,
                1
            ],
            "name": "wrist_A_R"
        },
        "wrist_L": {
            "children": [
                "index_0_L",
                "thumb_0_L"
            ],
            "jointId": "wrist_L",
            "matrix": [
                0.9685460925102235,
                0.15623351931571955,
                0.1936734914779662,
                0,
                -0.12375340398138862,
                0.9776777278005493,
                -0.16979688887161992,
                0,
                -0.21587827083919192,
                0.14048838949657283,
                0.9662605797882586,
                0,
                41.92745971679689,
                -0.00003051757815342171,
                -0.00006103515625,
                1
            ],
            "name": "wrist_L"
        },
        "wrist_R": {
            "children": [
                "thumb_0_R",
                "RWeapon",
                "index_0_R"
            ],
            "jointId": "wrist_R",
            "matrix": [
                0.9685460329055791,
                0.15623363852500927,
                0.19367362558841714,
                0,
                -0.12375360134880162,
                0.9776781928842968,
                -0.1697967993153311,
                0,
                -0.2158784535521846,
                0.14048820870715337,
                0.9662608173571168,
                0,
                -41.927398681640625,
                0.0000152587890625,
                0.000030517578125,
                1
            ],
            "name": "wrist_R"
        }
    },
    "samplers": {
        "sampler_0": {
            "magFilter": 9729,
            "minFilter": 9987,
            "wrapS": 10497,
            "wrapT": 10497
        }
    },
    "scene": "scene_0",
    "scenes": {
        "scene_0": {
            "nodes": [
                "Root_0",
                "obsidian_destroyer_model_LOD0",
                "obsidian_destroyer_head_model_LOD0",
                "obsidian_destroyer_horns_model_LOD0",
                "obsidian_destroyer_rocks_model_LOD0",
                "obsidian_destroyer_weapon_model_LOD0",
                "obsidian_destroyer_wings_model_LOD0"
            ]
        }
    },
    "shaders": {},
    "skins": {
        "skin_0": {
            "bindShapeMatrix": [
                1,
                0,
                0,
                0,
                0,
                1,
                0,
                0,
                0,
                0,
                1,
                0,
                0,
                0,
                0,
                1
            ],
            "inverseBindMatrices": {
                "bufferView": "bufferView_38",
                "byteOffset": 0,
                "count": 51,
                "type": 5126
            },
            "joints": [
                "bicep_A_L",
                "clavicle_A_L",
                "Root_0",
                "elbow_A_L",
                "Spine_0",
                "wrist_A_L",
                "Mid1_0_A_L",
                "Ring4_0",
                "Index1_0_A_L",
                "bicep_L",
                "elbow_L",
                "clavicle_L",
                "Spine_1",
                "Spine_3",
                "wrist_L",
                "WingBase0_0_L",
                "clavicle_R",
                "bicep_R",
                "Head_0",
                "jaw3_0",
                "clavicle_A_R",
                "index_1_R",
                "index_0_R",
                "wrist_R",
                "thumb_0_R",
                "elbow_R",
                "thumb_1_R",
                "Index1_0_A_R",
                "wrist_A_R",
                "elbow_A_R",
                "Ring5_0",
                "Mid1_0_A_R",
                "knee_R",
                "ankle_R",
                "toeBall_R",
                "thigh_R",
                "Spine0_1",
                "Spine0_2",
                "Spine0_0",
                "bicep_A_R",
                "index_0_L",
                "thumb_0_L",
                "thumb_1_L",
                "index_1_L",
                "thigh_L",
                "knee_L",
                "WingBend2_0",
                "WingBase1_0_R",
                "WingBend1_0",
                "ankle_L",
                "toeBall_L",
                "Head_1"
            ]
        },
        "skin_1": {
            "bindShapeMatrix": [
                1,
                0,
                0,
                0,
                0,
                1,
                0,
                0,
                0,
                0,
                1,
                0,
                0,
                0,
                0,
                1
            ],
            "inverseBindMatrices": {
                "bufferView": "bufferView_38",
                "byteOffset": 3328,
                "count": 3,
                "type": 5126
            },
            "joints": [
                "Head_1",
                "jaw3_0",
                "Head_0",
                "Spine_3",
                "Spine_1",
                "Spine_0",
                "Root_0"
            ]
        },
        "skin_2": {
            "bindShapeMatrix": [
                1,
                0,
                0,
                0,
                0,
                1,
                0,
                0,
                0,
                0,
                1,
                0,
                0,
                0,
                0,
                1
            ],
            "inverseBindMatrices": {
                "bufferView": "bufferView_38",
                "byteOffset": 3776,
                "count": 1,
                "type": 5126
            },
            "joints": [
                "Head_1",
                "Head_0",
                "Spine_3",
                "Spine_1",
                "Spine_0",
                "Root_0"
            ]
        },
        "skin_3": {
            "bindShapeMatrix": [
                1,
                0,
                0,
                0,
                0,
                1,
                0,
                0,
                0,
                0,
                1,
                0,
                0,
                0,
                0,
                1
            ],
            "inverseBindMatrices": {
                "bufferView": "bufferView_38",
                "byteOffset": 4160,
                "count": 20,
                "type": 5126
            },
            "joints": [
                "Spine_1",
                "Spine_0",
                "Spine_3",
                "clavicle_L",
                "jaw3_0",
                "Head_1",
                "Root_0",
                "clavicle_A_R",
                "Spine0_2",
                "Spine0_1",
                "thigh_R",
                "thigh_L",
                "Spine0_0",
                "clavicle_A_L",
                "WingBase1_0_R",
                "WingBend2_0",
                "toeBall_L",
                "clavicle_R",
                "WingBase0_0_L",
                "WingBend1_0",
                "Head_0",
                "ankle_L",
                "knee_L"
            ]
        },
        "skin_4": {
            "bindShapeMatrix": [
                1,
                0,
                0,
                0,
                0,
                1,
                0,
                0,
                0,
                0,
                1,
                0,
                0,
                0,
                0,
                1
            ],
            "inverseBindMatrices": {
                "bufferView": "bufferView_38",
                "byteOffset": 5632,
                "count": 1,
                "type": 5126
            },
            "joints": [
                "RWeapon",
                "wrist_R",
                "elbow_R",
                "bicep_R",
                "clavicle_R",
                "Spine_3",
                "Spine_1",
                "Spine_0",
                "Root_0"
            ]
        },
        "skin_5": {
            "bindShapeMatrix": [
                1,
                0,
                0,
                0,
                0,
                1,
                0,
                0,
                0,
                0,
                1,
                0,
                0,
                0,
                0,
                1
            ],
            "inverseBindMatrices": {
                "bufferView": "bufferView_38",
                "byteOffset": 6208,
                "count": 5,
                "type": 5126
            },
            "joints": [
                "WingBase0_0_L",
                "Root_0",
                "WingBase1_0_R",
                "WingBend1_0",
                "WingBend2_0"
            ]
        }
    },
    "techniques": {
        "technique_0": {
            "parameters": {},
            "pass": "defaultPass",
            "passes": {
                "defaultPass": {
                    "instanceProgram": {
                        "attributes": {},
                        "program": "",
                        "uniforms": {}
                    },
                    "states": {
                        "blendEnable": false,
                        "cullFaceEnable": false,
                        "depthMask": true,
                        "depthTestEnable": true
                    }
                }
            }
        }
    },
    "textures": {
        "Map #22": {
            "format": 6408,
            "internalFormat": 6408,
            "sampler": "sampler_0",
            "source": "image_0",
            "target": 3553
        },
        "Map #23": {
            "format": 6408,
            "internalFormat": 6408,
            "sampler": "sampler_0",
            "source": "image_1",
            "target": 3553
        },
        "Map #24": {
            "format": 6408,
            "internalFormat": 6408,
            "sampler": "sampler_0",
            "source": "image_2",
            "target": 3553
        },
        "Map #25": {
            "format": 6408,
            "internalFormat": 6408,
            "sampler": "sampler_0",
            "source": "image_3",
            "target": 3553
        },
        "Map #26": {
            "format": 6408,
            "internalFormat": 6408,
            "sampler": "sampler_0",
            "source": "image_4",
            "target": 3553
        },
        "Map #27": {
            "format": 6408,
            "internalFormat": 6408,
            "sampler": "sampler_0",
            "source": "image_5",
            "target": 3553
        }
    }
}