{
    "idle": [
        {
            "name": "idle_injured",
            "path": "heroes/slark/smd/idle_injured.smd"
        },
        {
            "name": "idle",
            "path": "heroes/slark/smd/idle.smd"
        },
        {
            "name": "idle2",
            "path": "heroes/slark/smd/idle2.smd"
        },
        {
            "name": "idle3",
            "path": "heroes/slark/smd/idle3.smd"
        }
    ],
    "attack": [
        {
            "name": "attack_injured",
            "path": "heroes/slark/smd/attack_injured.smd"
        },
        {
            "name": "attack",
            "path": "heroes/slark/smd/attack.smd"
        },
        {
            "name": "attack2",
            "path": "heroes/slark/smd/attack2.smd"
        }
    ],
    "run": [
        {
            "name": "run_injured",
            "path": "heroes/slark/smd/run_injured.smd"
        },
        {
            "name": "run",
            "path": "heroes/slark/smd/run.smd"
        }
    ],
    "default": {
        "name": "idle",
        "path": "heroes/slark/smd/idle.smd"
    }
}